{"2716231575":{"location":[44.7245328,18.7980293],"tp":"SU","tags":{"name":"Oglavak","name:sr":"Оглавак"}},"4201952951":{"location":[44.6350797,18.8435253],"tp":"SU","tags":{}},"4770695797":{"location":[44.6810457,18.8632521],"tp":"SU","tags":{"ele":"549","name":"Žutavka","name:sr":"Жутавка"}},"5276446981":{"location":[44.7242378,18.9781429],"tp":"SU","tags":{"ele":"210"}},"5344593508":{"location":[44.7023455,18.9547606],"tp":"SU","tags":{"ele":"298","name":"Obrenova Kosa","name:sr":"Обренова Коса"}},"5562087232":{"location":[44.6748084,18.8976686],"tp":"SU","tags":{"ele":"562","name":"Udrigovo","name:sr":"Удригово"}},"6260900557":{"location":[44.6032183,18.7504047],"tp":"SU","tags":{"ele":"738","name":"Cerje","name:sr":"Церје"}},"6260905003":{"location":[44.6107029,18.7201259],"tp":"SU","tags":{"ele":"720","name":"Gavranić","name:sr":"Гавранић","name:sr-Latn":"Gavranić"}},"6260907472":{"location":[44.6086113,18.743927],"tp":"SU","tags":{"ele":"803","name":"Greda","name:sr":"Греда"}},"6260908433":{"location":[44.6017583,18.7597165],"tp":"SU","tags":{"ele":"745","name":"Kapljevac","name:sr":"Капљевац"}},"6260909708":{"location":[44.6141036,18.7026401],"tp":"SU","tags":{"ele":"673","name":"Kicelj","name:sr":"Кицељ"}},"6260909945":{"location":[44.6202854,18.6767622],"tp":"SU","tags":{"ele":"694","name":"Kik","name:sr":"Кик"}},"6260935458":{"location":[44.5907166,18.7926461],"tp":"SU","tags":{"ele":"723","name":"Ploče","name:sr":"Плоче"}},"6260936660":{"location":[44.6319694,18.6795213],"tp":"SU","tags":{"ele":"759","name":"Ravni bukvik","name:sr":"Равни буквик"}},"6260939024":{"location":[44.5973477,18.7694237],"tp":"SU","tags":{"ele":"716","name":"Ravni lještak","name:sr":"Равни љештак"}},"6260939711":{"location":[44.6525492,18.6438398],"tp":"SU","tags":{"ele":"721","name":"Stublić","name:sr":"Стублић"}},"6260942416":{"location":[44.6373034,18.6630822],"tp":"SU","tags":{"ele":"711","name":"Zborište","name:sr":"Збориште"}},"6479119468":{"location":[44.6946304,18.9426527],"tp":"SU","tags":{"alt_name":"Đurin štab","alt_name:sr":"Ђурин штаб","ele":"315","name":"Jovanovića brdo","name:sr":"Јовановића брдо"}},"6479119469":{"location":[44.6963233,18.937327],"tp":"SU","tags":{"alt_name":"Mramorje","alt_name:sr":"Мраморје","ele":"312","name":"Lazića brdo","name:sr":"Лазића брдо","name:sr-Latn":"Lazića brdo"}},"7731057581":{"location":[44.6629511,18.9433138],"tp":"SU","tags":{"ele":"439","name":"Hajdukovo brdo","name:sr":"Хајдуково брдо"}},"8422445705":{"location":[44.6285319,18.6685757],"tp":"SU","tags":{"ele":"687","name":"M. Kik","name:sr":"М. Кик"}},"8573194668":{"location":[44.6714455,18.6425114],"tp":"SU","tags":{"ele":"690","name":"Oparkovica","name:sr":"Опарковица"}},"8708704153":{"location":[44.729502,18.9460061],"tp":"SU","tags":{"ele":"225","name":"Bojića brdo","name:sr":"Бојића брдо"}},"8708935270":{"location":[44.7098836,18.926447],"tp":"SU","tags":{"ele":"191","name":"Šuplje brdo","name:sr":"Шупље брдо","name:sr-Latn":"Šuplje brdo"}},"8708968976":{"location":[44.7173159,18.9193866],"tp":"SU","tags":{"ele":"228","name":"Musino brdo","name:sr":"Мусино брдо","name:sr-Latn":"Musino brdo"}},"8709053170":{"location":[44.715626,18.956501],"tp":"SU","tags":{"ele":"259","name":"Čardačič","name:sr":"Чардачић","name:sr-Latn":"Čardačić"}},"8813640128":{"location":[44.69586,18.9499161],"tp":"SU","tags":{"ele":"298","name":"Rudine","name:sr":"Рудине"}},"8813640129":{"location":[44.680471,18.9506847],"tp":"SU","tags":{"ele":"303","name":"Gavrića brdo","name:sr":"Гаврића брдо"}},"8813640130":{"location":[44.6723057,18.9458154],"tp":"SU","tags":{"ele":"321","name":"Ćirića brdo","name:sr":"Ћирића брдо"}},"8813640131":{"location":[44.6708251,18.9524802],"tp":"SU","tags":{"ele":"305"}},"8813640132":{"location":[44.660525,18.9514909],"tp":"SU","tags":{"ele":"405"}},"9386946007":{"location":[44.762689,18.9623594],"tp":"SU","tags":{"ele":"108.3"}},"9391603484":{"location":[44.7470323,18.9595096],"tp":"SU","tags":{"ele":"178"}},"9409920272":{"location":[44.7426371,18.9680556],"tp":"SU","tags":{"ele":"192","name":"Zorino brdo","name:sr":"Зорино брдо"}},"9409920273":{"location":[44.7298738,18.9658781],"tp":"SU","tags":{"ele":"207"}},"9409920274":{"location":[44.7315845,18.9757528],"tp":"SU","tags":{"ele":"206"}},"9409920275":{"location":[44.7364063,18.9486351],"tp":"SU","tags":{"ele":"204"}},"9415344657":{"location":[44.6918928,18.9231544],"tp":"SU","tags":{"ele":"331","name":"Kuline","name:sr":"Кулине"}},"9415344658":{"location":[44.6917243,18.9286435],"tp":"SU","tags":{"ele":"328"}},"9415344660":{"location":[44.6887105,18.9326651],"tp":"SU","tags":{"name":"Hadžino brdo","name:sr":"Хаџино брдо"}},"9887219941":{"location":[44.6846535,18.9245432],"tp":"SU","tags":{"ele":"330","name":"Bogdanovića brdo","name:sr":"Богдановића брдо"}},"9887219943":{"location":[44.6562748,18.9637419],"tp":"SU","tags":{"ele":"342"}},"9887219944":{"location":[44.6892243,18.9600869],"tp":"SU","tags":{"ele":"255"}},"9887219946":{"location":[44.6905008,18.9589007],"tp":"SU","tags":{"ele":"273","name":"Mirjanića brdo","name:sr":"Мирјанића брдо"}},"9887219947":{"location":[44.6980246,18.9753774],"tp":"SU","tags":{"ele":"226"}},"9887219948":{"location":[44.700076,18.9663726],"tp":"SU","tags":{"ele":"246"}},"9887219949":{"location":[44.6883634,18.9680201],"tp":"SU","tags":{"ele":"200"}},"9887219950":{"location":[44.6808739,18.9841445],"tp":"SU","tags":{"ele":"338","name":"Prokos","name:sr":"Прокос"}},"9908906887":{"location":[44.7238155,18.9593393],"tp":"SU","tags":{"ele":"235"}},"9908934952":{"location":[44.719055,18.9491678],"tp":"SU","tags":{"ele":"238"}},"9909159925":{"location":[44.694369,18.898882],"tp":"SU","tags":{"ele":"309"}},"9909205675":{"location":[44.6915395,18.89288],"tp":"SU","tags":{"ele":"278"}},"9909236740":{"location":[44.6695351,18.8952443],"tp":"SU","tags":{"ele":"534"}},"9909236742":{"location":[44.6614463,18.8834861],"tp":"SU","tags":{"ele":"411","name":"Busija","name:sr":"Бусија"}},"9933758972":{"location":[44.6373612,18.7599128],"tp":"SU","tags":{"ele":"503","name":"Gornja glavica","name:sr":"Горња главица"}},"9933796934":{"location":[44.6204053,18.7674628],"tp":"SU","tags":{"ele":"546","name":"Jelički vrh","name:sr":"Јелички врх"}},"9933805243":{"location":[44.6042563,18.7792923],"tp":"SU","tags":{"ele":"834","name":"Počivala","name:sr":"Почивала"}},"9933817831":{"location":[44.6115332,18.7792486],"tp":"SU","tags":{"ele":"842","name":"Međednik","name:sr":"Међедник"}},"9934005061":{"location":[44.6191024,18.7476921],"tp":"SU","tags":{"ele":"624","name":"Шкриљ","name:sr":"Шкриљ","name:sr-Latn":"Škrilj"}},"9934347150":{"location":[44.6566944,18.7665528],"tp":"SU","tags":{"ele":"499","name":"Стрнча брдо","name:sr-Latn":"Strnča brdo"}},"9934358319":{"location":[44.6503822,18.7537479],"tp":"SU","tags":{"ele":"456"}},"9934379476":{"location":[44.6512822,18.7976538],"tp":"SU","tags":{"ele":"317","name":"Спужовац","name:sr-Latn":"Spužovac"}},"9934381913":{"location":[44.644061,18.7828607],"tp":"SU","tags":{"ele":"342","name":"Гај","name:sr-Latn":"Gaj"}},"12383810573":{"location":[44.7343608,18.9495438],"tp":"SU","tags":{"ele":"220","name":"Granak","name:sr":"Гранак"}},"12430006718":{"location":[44.7265893,18.9165952],"tp":"SU","tags":{"ele":"186","name":"Kalat","name:sr":"Калат"}},"12430006719":{"location":[44.7316965,18.9223484],"tp":"SU","tags":{"ele":"184","name":"Čitluk","name:sr":"Читлук"}},"12628051173":{"location":[44.6366431,18.7479651],"tp":"SU","tags":{"ele":"551"}},"12628051174":{"location":[44.6493301,18.715682],"tp":"SU","tags":{"ele":"445","name":"Zasieka"}},"12628051175":{"location":[44.6770684,18.6615765],"tp":"SU","tags":{"ele":"543"}},"12628051176":{"location":[44.7021092,18.7401438],"tp":"SU","tags":{"ele":"529"}},"12628051179":{"location":[44.7063185,18.6394214],"tp":"SU","tags":{"ele":"548"}},"12628051180":{"location":[44.7283207,18.6703205],"tp":"SU","tags":{"ele":"640"}},"12785215688":{"location":[44.6705996,18.9231501],"tp":"SU","tags":{"ele":"409","name":"Oskruše","name:sr":"Оскруше"}},"12785215689":{"location":[44.6680125,18.9106928],"tp":"SU","tags":{"ele":"542","name":"Brezovača","name:sr":"Брезовача"}},"12785215691":{"location":[44.6651818,18.9147655],"tp":"SU","tags":{"ele":"521","name":"Mijajlovac","name:sr":"Мијајловац"}},"12785215692":{"location":[44.6500716,18.9069064],"tp":"SU","tags":{"ele":"326","name":"Kičin","name:sr":"Кичин"}},"12785215694":{"location":[44.6509308,18.9148369],"tp":"SU","tags":{"ele":"421","name":"Osjenjak","name:sr":"Осјењак"}},"12785215695":{"location":[44.6559281,18.9165852],"tp":"SU","tags":{"ele":"431","name":"Jagodnjak","name:sr":"Јагодњак"}},"12785227279":{"location":[44.7055571,18.8983537],"tp":"SU","tags":{"ele":"254","name":"Mejdani","name:sr":"Мејдани"}},"12785275752":{"location":[44.6880034,18.9101787],"tp":"SU","tags":{"ele":"371","name":"Sojskovača","name:sr":"Сојсковача"}},"12785275784":{"location":[44.6820166,18.9077195],"tp":"SU","tags":{"ele":"418"}},"12785460413":{"location":[44.6500854,18.9278287],"tp":"SU","tags":{"ele":"328","name":"Kućetina","name:sr":"Кућетина"}},"12794382919":{"location":[44.6799998,18.9179134],"tp":"SU","tags":{"ele":"446","name":"Goduš","name:sr":"Годуш"}},"12830260844":{"location":[44.7563144,18.9560293],"tp":"SU","tags":{"ele":"113.5"}},"12830260845":{"location":[44.7568427,18.9361649],"tp":"SU","tags":{"ele":"111"}},"12830260848":{"location":[44.7516553,18.9264339],"tp":"SU","tags":{"ele":"112.3"}},"12830260849":{"location":[44.7574241,18.9210619],"tp":"SU","tags":{"ele":"112.9"}},"12830260850":{"location":[44.75898,18.9112234],"tp":"SU","tags":{"ele":"114.8"}},"12830260853":{"location":[44.7524578,18.9056619],"tp":"SU","tags":{"ele":"115.7"}},"12830260854":{"location":[44.7529931,18.8876336],"tp":"SU","tags":{"ele":"123.5"}},"12830264608":{"location":[44.7510735,18.9707046],"tp":"SU","tags":{"ele":"166"}},"12830264609":{"location":[44.7505407,18.9612116],"tp":"SU","tags":{"ele":"167.6"}},"12830264613":{"location":[44.7750586,18.9632297],"tp":"SU","tags":{"ele":"104.9","name":"Gunjevine","name:sr":"Гуњевине"}},"12830264614":{"location":[44.756856,18.9476951],"tp":"SU","tags":{"ele":"168"}},"12830264616":{"location":[44.7517546,18.9447736],"tp":"SU","tags":{"ele":"181"}},"12833189035":{"location":[44.7448962,18.9446217],"tp":"SU","tags":{"ele":"201","name":"Tunjice","name:sr":"Туњице"}},"12833257476":{"location":[44.7076957,18.9774969],"tp":"SU","tags":{"ele":"241"}},"12833257477":{"location":[44.7187489,18.9830705],"tp":"SU","tags":{"ele":"204"}},"12833257479":{"location":[44.7085563,18.9690048],"tp":"SU","tags":{"ele":"251"}},"12833281821":{"location":[44.7169666,18.966585],"tp":"SU","tags":{"ele":"236"}},"12833299970":{"location":[44.7057842,18.9594336],"tp":"SU","tags":{"ele":"266"}},"12968841466":{"location":[44.5955002,18.9402877],"tp":"SU","tags":{"ele":"367"}},"12968939185":{"location":[44.6044404,18.9504822],"tp":"SU","tags":{"ele":"323","name":"Rust","name:sr":"Руст"}},"12968939187":{"location":[44.6055227,18.9704748],"tp":"SU","tags":{"ele":"454"}},"12968939188":{"location":[44.6066669,18.981583],"tp":"SU","tags":{"ele":"500","name":"Mramor","name:sr":"Мрамор"}},"12968944044":{"location":[44.6115268,18.9450968],"tp":"SU","tags":{"ele":"354"}},"12968944046":{"location":[44.6086588,18.9278104],"tp":"SU","tags":{"ele":"310","name":"Andrino brdo","name:sr":"Андрино брдо"}},"12968944047":{"location":[44.6171651,18.9262761],"tp":"SU","tags":{"ele":"390","name":"Numera","name:sr":"Нумера"}},"12969243038":{"location":[44.6241178,18.8774859],"tp":"SU","tags":{"ele":"442","name":"Svijetljika","name:sr":"Свијетљика"}}}