{"534094016":{"location":[49.0269584,84.8362872],"tp":"SU","ts":"2017-04-04T06:55:46Z","tags":{"name":"Майсаз","source":"GNS"}},"534094024":{"location":[48.956667,85.070556],"tp":"SU","ts":"2016-05-06T16:53:18Z","tags":{"name":"хребет Озерный","source":"GNS"}},"534094026":{"location":[48.950278,85.030556],"tp":"SU","ts":"2016-05-06T16:53:16Z","tags":{"name":"горы Шопканжол","source":"GNS"}},"534094028":{"location":[48.949167,84.956111],"tp":"SU","ts":"2016-05-06T16:53:14Z","tags":{"name":"горы Жайдак","source":"GNS"}},"534094041":{"location":[49.119722,84.889444],"tp":"SU","ts":"2017-04-04T06:55:46Z","tags":{"name":"Шыбык","source":"GNS"}},"534094055":{"location":[49.1,85],"tp":"SU","ts":"2017-04-04T06:55:46Z","tags":{"name":"Бернитаул","source":"GNS"}},"534094056":{"location":[49.079722,84.9525],"tp":"SU","ts":"2017-04-04T06:55:46Z","tags":{"name":"Шубаршилик","source":"GNS"}}}