{"310984983":{"location":[-33.4240075,151.3369241],"tp":"SU","tags":{"alt_name":"President's Hill","ele":"116","name":"Presidents Hill"}},"638688558":{"location":[-33.4233107,151.3493277],"tp":"SU","tags":{"name":"Mount Mouat"}},"3019437656":{"location":[-33.38725,151.18856],"tp":"SU","tags":{"ele":"309","man_made":"survey_point","name":"Mount Olive","wikidata":"Q21905846"}},"5136788459":{"location":[-33.3919386,151.3599537],"tp":"SU","tags":{"ele":"156","name":"Berrys Head"}},"5156399765":{"location":[-33.4061698,151.3904933],"tp":"SU","tags":{"ele":"200","name":"Mount Elliot"}},"8034939820":{"location":[-33.3147757,151.4050687],"tp":"SU","tags":{"ele":"156","name":"Mount Tangy Dangy"}},"8045806610":{"location":[-33.2330579,151.4012611],"tp":"SU","tags":{"ele":"124","name":"Mount Alison"}},"8051692670":{"location":[-33.2893528,151.2361983],"tp":"SU","tags":{"alt_name":"Mount Popran","ele":"363","name":"Mangrove Mountain"}},"8092263815":{"location":[-33.4069504,151.2970431],"tp":"SU","tags":{"alt_name":"Penang Mountain","description":"The Pacific Motorway was cut through this often gently sloping mountain, a plateau extends to the west and hosts a number of historic and active quarry locations.","ele":"267","name":"Mount Penang"}},"8150096057":{"location":[-33.2754927,151.420656],"tp":"SU","tags":{"alt_name":"Wyong Hill","ele":"107","name":"Chapmans Hill"}},"8581180902":{"location":[-33.3041857,151.3818613],"tp":"SU","tags":{"description":"The first school in this area, Kangy Angy School, sat on the eastern slope of this hill, near Zoriana Close.","ele":"160","name":"Cobbs Hill","note":"Not to be confused with Cobbs Hill Estate which is along Woodbury Park Drive. The town planners drew inspiration from historic place names, but the hill wasn't actually inside the estate.","source":"local knowledge;DCS NSW Topographic Map"}},"8788162194":{"location":[-33.2652225,151.4241832],"tp":"SU","tags":{"ele":"47","name":"Watanobbi Knoll"}},"9778294905":{"location":[-33.4265169,151.2209654],"tp":"SU","tags":{"ele":"230"}}}