{"428192272":{"location":[60.9940151,11.3388998],"tp":"SU","tags":{"ele":"767","name":"Nordhue"}},"701931532":{"location":[61.0364093,11.2598362],"tp":"SU","tags":{"alt_name":"Gjetholen","ele":"852","name":"Gitvola"}},"1007191241":{"location":[60.9315301,11.4050898],"tp":"SU","tags":{"ele":"591","name":"Narsæterberget"}},"1295166341":{"location":[60.9477018,11.3222735],"tp":"SU","tags":{"ele":"675","name":"Klekkefjellet"}},"1593404512":{"location":[60.9544135,11.2646096],"tp":"SU","tags":{"ele":"758","name":"Svaen"}},"6984891014":{"location":[60.961824,11.2662542],"tp":"SU","tags":{"ele":"740","name":"Veslesvaen"}},"8740653719":{"location":[61.0188653,11.5910714],"tp":"SU","tags":{"ele":"556","name":"Bjørnåsen"}},"8753769046":{"location":[61.0496724,11.4768278],"tp":"SU","tags":{"ele":"643","name":"Hyttmyrberget"}},"8753769048":{"location":[61.034592,11.4595824],"tp":"SU","tags":{"ele":"674","name":"Holshaugen"}},"8753769049":{"location":[61.0639491,11.5130892],"tp":"SU","tags":{"ele":"632","name":"Kråkberget"}},"8753769110":{"location":[61.0801622,11.5395336],"tp":"SU","tags":{"ele":"626","name":"Skjærnupen"}},"8753769111":{"location":[61.0837951,11.5109785],"tp":"SU","tags":{"ele":"614","name":"Lauvnubben"}},"8832556253":{"location":[60.9643787,11.5137956],"tp":"SU","tags":{"ele":"318","name":"Sæterberget"}},"8835860795":{"location":[60.9894065,11.3676142],"tp":"SU","tags":{"ele":"536","name":"Jerpåshaugen"}},"8835860796":{"location":[61.0019755,11.366695],"tp":"SU","tags":{"ele":"478","name":"Øvre Tørrholen"}},"8835878353":{"location":[61.023641,11.347326],"tp":"SU","tags":{"ele":"510","name":"Bjørnberget"}},"8835878354":{"location":[61.0190832,11.3016899],"tp":"SU","tags":{"ele":"665","name":"Fjælabuhøgda"}},"8835878439":{"location":[61.0074613,11.3340414],"tp":"SU","tags":{"ele":"729","name":"Nordhuehøgda"}},"8836516818":{"location":[61.0865783,11.5913986],"tp":"SU","tags":{"ele":"316","name":"Lindberget"}},"8847838912":{"location":[61.0655654,11.4731542],"tp":"SU","tags":{"ele":"609","name":"Kråksæterberget"}},"9223911234":{"location":[60.9354663,11.5731134],"tp":"SU","tags":{"ele":"376"}},"9223911235":{"location":[60.9383358,11.5868864],"tp":"SU","tags":{"ele":"384"}},"9223911236":{"location":[60.9407747,11.5885744],"tp":"SU","tags":{"ele":"389"}},"9223911237":{"location":[60.9719444,11.5045244],"tp":"SU","tags":{"ele":"307","name":"Oddsleppa"}},"9223911238":{"location":[60.9746696,11.504367],"tp":"SU","tags":{"ele":"337","name":"Svanåsen"}},"12327735646":{"location":[61.009529,11.3375926],"tp":"SU","tags":{"ele":"701","name":"Fjøsmyrhøgda"}},"12327741041":{"location":[61.034737,11.4200348],"tp":"SU","tags":{"ele":"376","name":"Skjelmohammeren"}},"12337239004":{"location":[61.0504563,11.4977624],"tp":"SU","tags":{"ele":"532","name":"Djupdalsbrenna"}},"12337239005":{"location":[61.0591416,11.4932614],"tp":"SU","tags":{"ele":"561","name":"Vesle Kråkberget"}},"12337239009":{"location":[60.9332711,11.3740499],"tp":"SU","tags":{"ele":"633","name":"Valberget"}},"12337239010":{"location":[60.9749917,11.4565491],"tp":"SU","tags":{"ele":"286","name":"Brennberget"}},"12347994055":{"location":[61.0239978,11.5028417],"tp":"SU","tags":{"ele":"392","name":"Høybrenntangen"}},"12387035934":{"location":[61.0757902,11.3968581],"tp":"SU","tags":{"ele":"396","name":"Harptjennsberget"}},"12387035935":{"location":[61.0534705,11.3073001],"tp":"SU","tags":{"ele":"606","name":"Søndre Kletten"}},"12387035936":{"location":[61.0644895,11.2919549],"tp":"SU","tags":{"ele":"725","name":"Nordre Kletten"}},"12387035937":{"location":[61.0625263,11.2553737],"tp":"SU","tags":{"ele":"713","name":"Nygardshauga"}},"12387035938":{"location":[61.0734754,11.3158206],"tp":"SU","tags":{"ele":"403","name":"Langdalsberget"}},"12387035939":{"location":[61.075154,11.3021584],"tp":"SU","tags":{"ele":"427","name":"Vårsæterberget"}},"12387035940":{"location":[61.070382,11.3016058],"tp":"SU","tags":{"ele":"498","name":"Djupdalsberget"}}}