{"2930876936":{"location":[48.3748892,37.9599059],"tp":"SU","tags":{"height":"30"}},"2945672627":{"location":[48.3433249,37.9566106],"tp":"SU","tags":{"height":"12","name":"Терикон шахти 19-20","name:uk":"Терикон шахти 19-20"}},"2945675275":{"location":[48.3429295,37.9596738],"tp":"SU","tags":{"height":"15"}},"2976903836":{"location":[48.3733035,37.9603725],"tp":"SU","tags":{}},"2976910504":{"location":[48.3593461,37.9427697],"tp":"SU","tags":{}},"2976910579":{"location":[48.3611815,37.9380909],"tp":"SU","tags":{"name":"Терикон шахти імени Гагарина","name:uk":"Терикон шахти імени Гагарина"}},"3379453415":{"location":[48.4016592,37.8188957],"tp":"SU","tags":{}},"3379453912":{"location":[48.3621758,37.9339975],"tp":"SU","tags":{"height":"10"}},"3379453938":{"location":[48.4161308,37.8176953],"tp":"SU","tags":{"height":"15"}},"3379453952":{"location":[48.3283772,37.9342191],"tp":"SU","tags":{"height":"19","name":"Відвал шахти ім. Леніна","name:ru":"отвал шахты имени Ленина","name:uk":"Відвал шахти ім. Леніна"}},"3379453976":{"location":[48.3647865,37.9438914],"tp":"SU","tags":{"height":"20"}},"3379453977":{"location":[48.4074563,37.815216],"tp":"SU","tags":{"height":"20"}},"3379453995":{"location":[48.4052032,37.8105984],"tp":"SU","tags":{"height":"25"}},"3379453997":{"location":[48.4103683,37.8360548],"tp":"SU","tags":{"height":"26"}},"3379454011":{"location":[48.3583557,37.9005887],"tp":"SU","tags":{"height":"3"}},"3379454027":{"location":[48.3638016,37.963207],"tp":"SU","tags":{"height":"30"}},"3379454035":{"location":[48.3494293,37.9240817],"tp":"SU","tags":{"height":"35"}},"3379454036":{"location":[48.3539466,37.9441828],"tp":"SU","tags":{"height":"35"}},"3379454037":{"location":[48.3861817,37.8275298],"tp":"SU","tags":{"height":"35"}},"3379454061":{"location":[48.3576955,37.8838279],"tp":"SU","tags":{"height":"40"}},"3379454064":{"location":[48.374737,37.8762278],"tp":"SU","tags":{"height":"40","name":"Терикон шахти імені Артема","name:ru":"Террикон шахты имени Артема","name:uk":"Терикон шахти імені Артема"}},"3379454065":{"location":[48.3943707,37.8984283],"tp":"SU","tags":{"height":"40","name":"Терикон шахти Північна","name:ru":"террикон шахты Северная","name:uk":"Терикон шахти Північна"}},"3379454066":{"location":[48.4095278,37.8376144],"tp":"SU","tags":{"height":"40","name":"Терикон шахти Фомиха","name:ru":"Террикон шахты Фомиха","name:uk":"Терикон шахти Фоміха"}},"3379454088":{"location":[48.3359225,37.9501948],"tp":"SU","tags":{"height":"5"}},"3379454090":{"location":[48.3503974,37.934375],"tp":"SU","tags":{"height":"5"}},"3379454096":{"location":[48.389201,37.8330436],"tp":"SU","tags":{"height":"50"}},"3379454140":{"location":[48.3728361,37.847405],"tp":"SU","tags":{"height":"70","name":"Терикон шахти \"Валюга\"","name:ru":"Террикон шахты \"Валюга\"","name:uk":"Терикон шахти \"Валюга\""}},"3379454142":{"location":[48.3912137,37.8273041],"tp":"SU","tags":{"height":"70"}},"3379454143":{"location":[48.4028841,37.8285713],"tp":"SU","tags":{"height":"70","name":"Відвал шахти №10","name:uk":"Відвал шахти №10"}},"3379454153":{"location":[48.3780532,37.9319236],"tp":"SU","tags":{"height":"8"}},"3379454154":{"location":[48.3798857,37.9215547],"tp":"SU","tags":{"height":"8","name":"Відвал шахти Північна","name:uk":"Відвал шахти Північна"}},"3379454155":{"location":[48.3830437,37.9297394],"tp":"SU","tags":{"height":"88","name":"терикон шахти Восточна","name:ru":"террикон шахты Восточная","name:uk":"терикон шахти Східна"}},"3379454157":{"location":[48.3859102,37.8703569],"tp":"SU","tags":{"height":"80","name":"Терикон шахти Нова","name:ru":"Террикон шахты Новая","name:uk":"Терикон шахти Нова"}},"3379454158":{"location":[48.4093801,37.8276076],"tp":"SU","tags":{"height":"80","name":"Терикон шахти №12","name:ru":"Террикон шахты №12","name:uk":"Терикон шахти №12"}},"3379454159":{"location":[48.41024,37.8512916],"tp":"SU","tags":{"height":"80","name":"Терикон шахти Торецька","name:ru":"Террикон шахты Торецкая","name:uk":"Терикон шахти Торецька"}},"5070930829":{"location":[48.3372468,37.8765073],"tp":"SU","tags":{"ele":"169.4"}},"5070930830":{"location":[48.3148074,37.8636076],"tp":"SU","tags":{"ele":"154.3"}},"5070930831":{"location":[48.3005067,37.8826191],"tp":"SU","tags":{"ele":"180.9"}},"5070930832":{"location":[48.2875869,37.8853013],"tp":"SU","tags":{"ele":"181.3"}},"5070930855":{"location":[48.2938412,37.8321753],"tp":"SU","tags":{"ele":"180.0"}},"5070931143":{"location":[48.3047652,37.8343776],"tp":"SU","tags":{"ele":"181.6"}},"5070931147":{"location":[48.3169529,37.8142503],"tp":"SU","tags":{"ele":"198.8"}},"5070931148":{"location":[48.3155972,37.7995089],"tp":"SU","tags":{"ele":"222.0"}},"5070931149":{"location":[48.3326612,37.7906684],"tp":"SU","tags":{"ele":"210.8"}},"5070931150":{"location":[48.3447057,37.8078167],"tp":"SU","tags":{"ele":"164.3"}},"5070931154":{"location":[48.3570773,37.8029851],"tp":"SU","tags":{"ele":"183.7"}},"9960215212":{"location":[48.4000229,37.7968846],"tp":"SU","tags":{"name":"Териконник шахти Добрянського (Сорочиха)","name:uk":"Териконник шахти Добрянського (Сорочиха)"}},"9960215230":{"location":[48.3640515,37.9129726],"tp":"SU","tags":{"name":"Терикон шахти Південна","name:ru":"террикон шахты Южная","name:uk":"Терикон шахти Південна"}},"9960215231":{"location":[48.3545251,37.9340343],"tp":"SU","tags":{"name":"терикон шахти \"41-біс\"","name:ru":"террикон шахты \"41-бис\"","name:uk":"терикон шахти \"41-біс\""}}}