{"357924071":{"location":[34.7617603,-88.7125555],"tp":"SU","tags":{"ele":"161","gnis:feature_id":"666339","name":"Antioch Hill","wikidata":"Q31611760"}},"357924301":{"location":[34.8037034,-88.6758873],"tp":"SU","tags":{"ele":"189","gnis:feature_id":"666481","name":"Bald Hill","wikidata":"Q31611856"}},"357926358":{"location":[34.7895373,-88.707555],"tp":"SU","tags":{"ele":"188","gnis:feature_id":"667513","name":"Bragg Mountain","wikidata":"Q31612132"}},"357929107":{"location":[34.8262033,-88.7219994],"tp":"SU","tags":{"ele":"212","gnis:feature_id":"668987","name":"Crow Mountain","wikidata":"Q31612454"}},"357929113":{"location":[34.8600915,-88.7331105],"tp":"SU","tags":{"ele":"221","gnis:feature_id":"668995","name":"Crum Mountain","wikidata":"Q31612466"}},"357932761":{"location":[34.8109261,-88.7564451],"tp":"SU","tags":{"ele":"177","gnis:feature_id":"670851","name":"Ham Hill"}},"357932827":{"location":[34.8570353,-88.6467192],"tp":"SU","tags":{"ele":"158","gnis:feature_id":"670877","name":"Hancock Hill","wikidata":"Q31612774"}},"357934858":{"location":[34.7067626,-88.8531153],"tp":"SU","tags":{"ele":"177","gnis:feature_id":"672081","name":"Kelley Hill"}},"357934909":{"location":[34.8700903,-88.6164404],"tp":"SU","tags":{"ele":"140","gnis:feature_id":"672130","name":"Kimmons Hill","wikidata":"Q31612999"}},"357935004":{"location":[34.6092641,-88.7192224],"tp":"SU","tags":{"ele":"222","gnis:feature_id":"672195","name":"Kitchen Mountain"}},"357937199":{"location":[34.759816,-88.7397785],"tp":"SU","tags":{"ele":"159","gnis:feature_id":"673520","name":"Michales Hill","wikidata":"Q31613259"}},"357939944":{"location":[34.8545363,-88.7683893],"tp":"SU","tags":{"ele":"173","gnis:feature_id":"674547","name":"Neil Hill"}},"357941505":{"location":[34.6103756,-88.7797796],"tp":"SU","tags":{"ele":"209","gnis:feature_id":"675088","name":"Oak Mill Hill"}},"357945342":{"location":[34.8300924,-88.7658895],"tp":"SU","tags":{"ele":"191","gnis:feature_id":"676821","name":"Rogers Hill"}},"357945347":{"location":[34.8623128,-88.6242185],"tp":"SU","tags":{"ele":"155","gnis:feature_id":"676822","name":"Rogers Hill","wikidata":"Q31613868"}},"357945748":{"location":[34.6309305,-88.7720016],"tp":"SU","tags":{"ele":"195","gnis:feature_id":"676998","name":"Sadler Hills"}},"357947733":{"location":[34.7728716,-88.770057],"tp":"SU","tags":{"ele":"204","gnis:feature_id":"677808","name":"Silver Springs Hill"}},"357949715":{"location":[34.6109308,-88.7303338],"tp":"SU","tags":{"ele":"228","gnis:feature_id":"678772","name":"Tippah Hills"}},"357951564":{"location":[34.8737027,-88.7925566],"tp":"SU","tags":{"ele":"156","gnis:feature_id":"679718","name":"Williams Graveyard Hill","wikidata":"Q31614576"}}}