{"332373558":{"location":[53.7194043,-8.0704404],"tp":"SU","tags":{"ele":"315.6","ele:local":"262","ele:tm75":"262","ele:wgs84":"315.6","ele_local":"262","iemv:gpsname10":"SlvBawn","iemv:gpsname6":"Slv263","iemv:importtime":"2009-01-16 10:19:20","iemv:lat":"53.719404310","iemv:lon":"-8.070440373","iemv:mtnarea":"North Midlands","iemv:mtnindex":"991","iemv:sourcetime":"2009-01-16 10:14:05","name":"Slieve Bawn","name:en":"Slieve Bawn","name:ga":"Sliabh Bána","note":"Irish summit data imported from mountainviews.ie","source":"Mountain Views","source:name":"www.mountainviews.ie/mv/index.php?mtnindex=991","wikidata":"Q7540423"}},"10757153057":{"location":[53.6507748,-8.0701661],"tp":"SU","tags":{}}}