{"6295694894":{"location":[65.5762035,19.61923],"tp":"SU","ts":"2024-08-26T09:38:47Z","tags":{"name":"Krampoberget","name:sju":"Krámpuovárrie","name:sv":"Krampoberget","wikidata":"Q31265708"}},"6297337363":{"location":[65.5741137,19.5268432],"tp":"SU","ts":"2019-02-23T12:08:13Z","tags":{"ele":"503","name":"Nyträskberget"}},"7352469041":{"location":[65.5589659,19.6288132],"tp":"SU","ts":"2020-03-31T20:28:37Z","tags":{"name":"Sikträskberget"}},"7352469042":{"location":[65.5667687,19.6428036],"tp":"SU","ts":"2020-03-31T20:28:37Z","tags":{"name":"Majaliden"}},"7352469043":{"location":[65.587884,19.6275043],"tp":"SU","ts":"2024-08-26T09:38:47Z","tags":{"name":"Lillberget","wikidata":"Q31265662"}},"7352469044":{"location":[65.6076353,19.6366453],"tp":"SU","ts":"2024-08-26T09:38:48Z","tags":{"name":"Guortesliden","wikidata":"Q31265844"}},"7352469045":{"location":[65.6162474,19.5675516],"tp":"SU","ts":"2020-03-31T20:28:37Z","tags":{"name":"Hatten"}},"7352469046":{"location":[65.6013871,19.5495486],"tp":"SU","ts":"2020-03-31T20:28:37Z","tags":{"name":"Deppisliden"}},"7352469047":{"location":[65.6134656,19.4383764],"tp":"SU","ts":"2020-03-31T20:28:37Z","tags":{"name":"Stormyrberget"}},"7352469048":{"location":[65.6054375,19.4173479],"tp":"SU","ts":"2020-03-31T20:28:37Z","tags":{"name":"Tjåkasberget"}},"7352469049":{"location":[65.595359,19.4670009],"tp":"SU","ts":"2020-03-31T20:28:37Z","tags":{"name":"Renträskberget"}},"7352469050":{"location":[65.5842655,19.4511222],"tp":"SU","ts":"2020-03-31T20:28:37Z","tags":{"name":"Västerberget"}},"7352469051":{"location":[65.5793512,19.4565725],"tp":"SU","ts":"2020-03-31T20:28:37Z","tags":{"name":"Tvärberget"}},"7352469052":{"location":[65.5748797,19.4804763],"tp":"SU","ts":"2020-03-31T20:28:37Z","tags":{"name":"Sör-brännberget"}},"7352469053":{"location":[65.5479012,19.4587397],"tp":"SU","ts":"2020-03-31T20:28:37Z","tags":{"name":"Lappskottbackberget"}},"7352469054":{"location":[65.5406347,19.468503],"tp":"SU","ts":"2020-03-31T20:28:37Z","tags":{"name":"Fásstabuoldda"}},"7352469055":{"location":[65.5277045,19.4874072],"tp":"SU","ts":"2020-03-31T20:28:37Z","tags":{"name":"Bollberget"}},"7352469056":{"location":[65.5146879,19.5186496],"tp":"SU","ts":"2020-03-31T20:28:37Z","tags":{"name":"Njaukaberget"}},"7352469057":{"location":[65.517836,19.4586539],"tp":"SU","ts":"2020-03-31T20:28:37Z","tags":{"name":"Hammarberget"}},"7352469058":{"location":[65.5317754,19.4523668],"tp":"SU","ts":"2020-03-31T20:28:37Z","tags":{"name":"Skällberget"}},"7352469059":{"location":[65.5596051,19.4130564],"tp":"SU","ts":"2020-03-31T20:28:37Z","tags":{"name":"Lillberget"}},"7352469060":{"location":[65.569094,19.4622802],"tp":"SU","ts":"2020-03-31T20:28:37Z","tags":{"name":"Harrejaurliden"}},"7352486762":{"location":[65.5144656,19.4082498],"tp":"SU","ts":"2020-03-31T20:28:37Z","tags":{"name":"Tallberget"}},"7352486763":{"location":[65.5265934,19.4088077],"tp":"SU","ts":"2020-03-31T20:28:37Z","tags":{"name":"Östra Luspenåive"}},"7352486764":{"location":[65.5145634,19.3697119],"tp":"SU","ts":"2020-03-31T20:28:37Z","tags":{"ele":"483","name":"Bergmyrberget"}},"7352486765":{"location":[65.5266112,19.3675232],"tp":"SU","ts":"2020-03-31T20:28:37Z","tags":{"name":"Skravelberget"}},"7352486766":{"location":[65.5325663,19.3718147],"tp":"SU","ts":"2020-03-31T20:28:37Z","tags":{"name":"Västra Luspenåive"}},"7352486767":{"location":[65.5382269,19.337858],"tp":"SU","ts":"2020-03-31T20:28:37Z","tags":{"name":"Kåtaberget"}},"7360002494":{"location":[65.5424382,19.5496774],"tp":"SU","ts":"2020-04-02T20:05:24Z","tags":{"name":"Ellevárrie"}},"7360002495":{"location":[65.5361032,19.5885157],"tp":"SU","ts":"2021-08-19T14:14:56Z","tags":{"name":"Kåtaberget"}},"7360002496":{"location":[65.5283445,19.6031713],"tp":"SU","ts":"2020-04-02T20:05:24Z","tags":{"name":"Svartberget"}}}