{"10782748184":{"location":[78.2281938,16.5300046],"tp":"SU","tags":{"ele":"957","name":"Arctowskifjellet","source":"https://data.npolar.no/placename/8e4063a5-f38d-5149-b957-c9a86fc43275"}},"13538941813":{"location":[78.2637512,16.5805221],"tp":"SU","tags":{"ele":"911","name":"Oliviertoppen","source":"https://data.npolar.no/placename/af7180fc-d9ce-5339-9cf5-dd29b15a367a"}},"13538941814":{"location":[78.2700593,16.5297062],"tp":"SU","tags":{"ele":"922","name":"Albert Bruntoppen","source":"https://data.npolar.no/placename/e700d178-49f7-513a-940a-935faa077b53"}},"13541130748":{"location":[78.2774865,16.6563892],"tp":"SU","tags":{"ele":"867","name":"Gattytoppen","source":"https://data.npolar.no/placename/ac785a36-f2b6-52eb-97e5-1ff94ab79e94"}},"13541130749":{"location":[78.2687641,16.6545438],"tp":"SU","tags":{"ele":"915","name":"Ile de Francekollen","source":"https://data.npolar.no/placename/0a9053de-6ac3-5843-a1c7-dd0ce2234acd"}},"13541130750":{"location":[78.2638506,16.6390943],"tp":"SU","tags":{"ele":"926","name":"Lusitaniafjellet","source":"https://data.npolar.no/placename/2b4cf2d6-d842-5c0e-90d2-96418407de2f"}},"13541130751":{"location":[78.2515797,16.6447162],"tp":"SU","tags":{"ele":"890","name":"Valmuetoppen","source":"https://data.npolar.no/placename/e58265d1-c983-54d7-84bb-299f42951442"}},"13541130752":{"location":[78.2581927,16.7017507],"tp":"SU","tags":{"ele":"826","name":"Roulletegga","source":"https://data.npolar.no/placename/af9d2e4a-0a6c-5b25-a05a-d101d49f90c9"}},"13541130753":{"location":[78.2502427,16.794362],"tp":"SU","tags":{"ele":"683","name":"Grusryggen","source":"https://data.npolar.no/placename/7453991b-ad44-58b3-98a0-a330cc86c936"}},"13541130754":{"location":[78.2409669,16.7604159],"tp":"SU","tags":{"ele":"845","name":"Duboistoppen","source":"https://data.npolar.no/placename/f53c46f1-cb7d-5660-85ab-ec143b1bc478"}}}