{"5744833368":{"location":[13.5921821,-87.7277044],"tp":"SU","ts":"2018-07-07T05:20:49Z","tags":{"ele":"308","name":"Cerro del Ujushte"}},"5744833387":{"location":[13.600987,-87.7529458],"tp":"SU","ts":"2022-02-08T20:54:39Z","tags":{"name":"Cerro El Nancito"}},"5744834424":{"location":[13.5874608,-87.759021],"tp":"SU","ts":"2018-07-07T05:20:53Z","tags":{"name":"Cerro Largo"}},"5744834425":{"location":[13.5826487,-87.7588804],"tp":"SU","ts":"2018-07-07T05:20:53Z","tags":{"name":"Cerro La Peña"}},"9922778902":{"location":[13.8812085,-87.7230898],"tp":"SU","ts":"2022-07-31T16:20:58Z","tags":{"name":"Piedra Gorda"}},"13123924744":{"location":[13.9044116,-87.8811209],"tp":"SU","ts":"2025-09-06T20:13:07Z","tags":{"name":"Loma El Encinal"}},"13123924745":{"location":[13.9005605,-87.8732068],"tp":"SU","ts":"2025-09-06T20:13:07Z","tags":{"name":"Cerro Grande"}},"5413465666":{"location":[13.9169954,-87.8193237],"tp":"SU","ts":"2018-02-15T02:43:27Z","tags":{"name":"Cerro El Chapín"}},"5413465667":{"location":[13.9094087,-87.8004045],"tp":"SU","ts":"2018-02-15T02:43:27Z","tags":{"name":"Cerro El Cimarrion"}},"5413465998":{"location":[13.9069579,-87.8133107],"tp":"SU","ts":"2018-02-15T02:43:31Z","tags":{"name":"Cerro Guanacaste"}},"5982587748":{"location":[13.7491661,-87.7610255],"tp":"SU","ts":"2018-10-14T07:22:14Z","tags":{"ele":"377","name":"Cerro Guaripe"}},"12140803899":{"location":[13.6897309,-87.7736211],"tp":"SU","ts":"2024-08-27T20:22:24Z","tags":{"ele":"298","name":"Cerro Managua"}},"12140803900":{"location":[13.6841811,-87.7755085],"tp":"SU","ts":"2024-08-27T20:22:24Z","tags":{"ele":"268","name":"Cerro El Tigre"}},"12140823101":{"location":[13.6857538,-87.7574535],"tp":"SU","ts":"2024-08-27T20:22:24Z","tags":{"ele":"193"}},"12140823104":{"location":[13.6808576,-87.7623311],"tp":"SU","ts":"2024-08-27T20:22:24Z","tags":{"ele":"215","name":"Cerro El Chaguite","population":"215"}},"12140823105":{"location":[13.6612308,-87.7806493],"tp":"SU","ts":"2024-08-27T20:22:24Z","tags":{"ele":"235.10","name":"Cerro Jaguito"}},"12140823106":{"location":[13.6552674,-87.8155609],"tp":"SU","ts":"2024-08-27T20:22:24Z","tags":{"ele":"252","name":"Cerro Guachipilin"}},"12140823107":{"location":[13.6579155,-87.831504],"tp":"SU","ts":"2024-08-27T20:22:24Z","tags":{"ele":"312.12","name":"Cerro El Platanar"}},"12140823108":{"location":[13.6498878,-87.8266546],"tp":"SU","ts":"2024-08-27T20:22:24Z","tags":{"ele":"178","name":"Cerro La Ramada"}},"12140823109":{"location":[13.6446748,-87.832491],"tp":"SU","ts":"2024-08-27T20:22:24Z","tags":{"ele":"210","name":"Cerro Peña Gorda"}},"12168421431":{"location":[13.587341,-87.8687198],"tp":"SU","ts":"2024-09-10T16:28:18Z","tags":{"ele":"356","name":"Cerro Las Marias"}},"12168421432":{"location":[13.5883712,-87.8638909],"tp":"SU","ts":"2024-09-10T16:28:18Z","tags":{"ele":"310","name":"Cerro Maculis"}},"12168421433":{"location":[13.5905682,-87.8570167],"tp":"SU","ts":"2024-09-10T16:28:18Z","tags":{"ele":"231","name":"Cerro El Infiernillo"}},"12168421434":{"location":[13.5850302,-87.8610329],"tp":"SU","ts":"2024-09-10T16:28:18Z","tags":{"ele":"287","name":"Cerro Pasaquina"}},"12168421436":{"location":[13.5960641,-87.8424209],"tp":"SU","ts":"2024-09-10T16:28:18Z","tags":{"ele":"125","name":"Cerro El Picacho"}},"12168421437":{"location":[13.6024877,-87.8496736],"tp":"SU","ts":"2024-09-10T16:28:18Z","tags":{"ele":"156.07","name":"Cerro El Jiote"}},"12168421438":{"location":[13.6058159,-87.7828336],"tp":"SU","ts":"2024-09-10T16:28:18Z","tags":{"name":"Cerro Chino"}},"12168421439":{"location":[13.610842,-87.7869153],"tp":"SU","ts":"2024-09-10T16:28:18Z","tags":{"ele":"410.21","name":"Cerro Cerco de Piedra"}},"12168421440":{"location":[13.5960479,-87.7873056],"tp":"SU","ts":"2024-09-10T16:28:18Z","tags":{"ele":"303.90","name":"Cerro El Coyotero"}},"12168421441":{"location":[13.6281007,-87.785777],"tp":"SU","ts":"2024-09-10T16:28:18Z","tags":{"ele":"215","name":"Cerro El Gaspar"}},"13123924743":{"location":[13.8836623,-87.8882683],"tp":"SU","ts":"2025-09-06T20:13:07Z","tags":{"name":"Cerro Upire"}}}