{"2309224504":{"location":[40.1891703,25.8572117],"tp":"SU","ts":"2020-10-26T17:23:00Z","tags":{"ele":"350","name":"Karadoğan Tepesi","source":"cyclemap"}},"3744208476":{"location":[40.1966263,25.8242498],"tp":"SU","ts":"2020-12-20T00:06:54Z","tags":{"ele":"600","name":"Tepeköy Tepesi","name:en":"Tepeköy Hill","source":"cyclemap"}},"4143269089":{"location":[40.2337746,25.9298243],"tp":"SU","ts":"2024-01-22T14:54:53Z","tags":{"ele":"135","name":"Gözetme Tepesi","name:en":"Gözetme Hill","source":"http://www.geonames.org/7318654/goezetme-tepesi.html","wikidata":"Q32138650"}},"4143282957":{"location":[40.1985918,25.7786759],"tp":"SU","ts":"2016-04-28T07:56:09Z","tags":{"ele":"150","name":"Keltepe","source":"http://www.geonames.org/7318658/keltepe.html"}},"8047954318":{"location":[40.1937004,25.8590805],"tp":"SU","ts":"2021-04-19T10:09:01Z","tags":{"ele":"360","source":"OpenTopoMap"}},"8047954319":{"location":[40.2151567,25.856967],"tp":"SU","ts":"2021-04-19T10:09:01Z","tags":{"ele":"227","source":"OpenTopoMap"}},"8047954320":{"location":[40.2209324,25.9240866],"tp":"SU","ts":"2021-04-19T10:21:02Z","tags":{"ele":"301","source":"OpenTopoMap"}},"8047954321":{"location":[40.2214209,25.9163977],"tp":"SU","ts":"2022-09-29T11:51:06Z","tags":{"ele":"386","name":"Komando Tepesi","source":"OpenTopoMap"}},"8047954322":{"location":[40.1962901,25.936768],"tp":"SU","ts":"2021-04-19T10:21:02Z","tags":{"ele":"344","source":"OpenTopoMap"}},"8047954323":{"location":[40.2010759,25.9334636],"tp":"SU","ts":"2021-04-19T10:21:02Z","tags":{"ele":"349","source":"OpenTopoMap"}},"8047954324":{"location":[40.2010185,25.928539],"tp":"SU","ts":"2021-04-19T10:21:02Z","tags":{"ele":"304","source":"OpenTopoMap"}},"8047954325":{"location":[40.209655,25.9469819],"tp":"SU","ts":"2021-04-19T10:21:02Z","tags":{"ele":"261","source":"OpenTopoMap"}},"8047954326":{"location":[40.2377282,25.9451741],"tp":"SU","ts":"2021-04-19T10:21:02Z","tags":{"ele":"93","source":"OpenTopoMap"}},"8047954327":{"location":[40.2326256,25.9239149],"tp":"SU","ts":"2021-04-19T10:21:02Z","tags":{"ele":"435","source":"OpenTopoMap"}},"8047954328":{"location":[40.2298243,25.9233892],"tp":"SU","ts":"2021-04-19T10:21:02Z","tags":{"ele":"430","source":"OpenTopoMap"}},"8047954329":{"location":[40.2322284,25.9325945],"tp":"SU","ts":"2024-01-22T14:54:53Z","tags":{"ele":"329","source":"OpenTopoMap","wikidata":"Q32138650"}},"8047954330":{"location":[40.2251143,25.9318113],"tp":"SU","ts":"2021-04-19T10:21:02Z","tags":{"ele":"342","source":"OpenTopoMap"}},"8048007185":{"location":[40.1794061,25.9228743],"tp":"SU","ts":"2024-01-27T14:52:11Z","tags":{"ele":"419","name":"Keklik Tepesi","source":"OpenTopoMap"}},"8048007188":{"location":[40.2014283,25.7977223],"tp":"SU","ts":"2021-04-19T10:09:01Z","tags":{"ele":"386","source":"OpenTopoMap"}},"8048007189":{"location":[40.1975604,25.8046424],"tp":"SU","ts":"2021-04-19T10:09:01Z","tags":{"ele":"499","source":"OpenTopoMap"}},"8048007190":{"location":[40.196536,25.8082259],"tp":"SU","ts":"2021-04-19T10:09:01Z","tags":{"ele":"540","source":"OpenTopoMap"}},"8048007193":{"location":[40.1788938,25.8060265],"tp":"SU","ts":"2021-04-19T10:09:01Z","tags":{"ele":"585","source":"OpenTopoMap"}},"8048007194":{"location":[40.1819759,25.8047551],"tp":"SU","ts":"2021-04-19T10:09:01Z","tags":{"ele":"585","source":"OpenTopoMap"}},"8048007196":{"location":[40.1843898,25.7962632],"tp":"SU","ts":"2021-04-19T10:09:01Z","tags":{"ele":"652","source":"OpenTopoMap"}},"8640016076":{"location":[40.1956755,25.8123994],"tp":"SU","ts":"2021-04-19T10:09:01Z","tags":{"ele":"510","source":"OpenTopoMap"}},"8640016077":{"location":[40.1952657,25.8161867],"tp":"SU","ts":"2021-04-19T10:09:01Z","tags":{"ele":"539","source":"OpenTopoMap"}},"8640016082":{"location":[40.2205023,25.8719873],"tp":"SU","ts":"2021-04-19T10:09:01Z","tags":{"ele":"202","source":"OpenTopoMap"}},"8640016083":{"location":[40.1943315,25.7569098],"tp":"SU","ts":"2021-04-19T10:09:01Z","tags":{"ele":"50","source":"OpenTopoMap"}},"8640016095":{"location":[40.1928399,25.9383344],"tp":"SU","ts":"2021-04-19T10:21:02Z","tags":{"ele":"313","source":"OpenTopoMap"}},"8640016096":{"location":[40.1898895,25.94769],"tp":"SU","ts":"2021-04-19T10:21:02Z","tags":{"ele":"271","source":"OpenTopoMap"}},"8640016097":{"location":[40.2302667,25.9170913],"tp":"SU","ts":"2021-04-19T10:21:02Z","tags":{"ele":"301","source":"OpenTopoMap"}},"8640016098":{"location":[40.2148003,25.972023],"tp":"SU","ts":"2021-04-19T10:21:02Z","tags":{"ele":"90","source":"OpenTopoMap"}},"8640016099":{"location":[40.2117198,25.966959],"tp":"SU","ts":"2021-04-19T10:21:02Z","tags":{"ele":"135","source":"OpenTopoMap"}},"8640016100":{"location":[40.2105071,25.9609079],"tp":"SU","ts":"2021-04-19T10:21:02Z","tags":{"ele":"195","source":"OpenTopoMap"}},"8640016101":{"location":[40.2144726,25.9596633],"tp":"SU","ts":"2021-04-19T10:21:02Z","tags":{"ele":"226","source":"OpenTopoMap"}},"8640016102":{"location":[40.2048043,25.9590625],"tp":"SU","ts":"2021-04-19T10:21:02Z","tags":{"ele":"148","source":"OpenTopoMap"}},"8640016103":{"location":[40.2067709,25.953741],"tp":"SU","ts":"2021-04-19T10:21:02Z","tags":{"ele":"213","source":"OpenTopoMap"}},"8640016114":{"location":[40.2046896,25.7931733],"tp":"SU","ts":"2021-04-19T10:09:01Z","tags":{"ele":"283","source":"OpenTopoMap"}},"8640016115":{"location":[40.1980193,25.7764792],"tp":"SU","ts":"2021-04-19T10:09:01Z","tags":{"ele":"243","source":"OpenTopoMap"}},"8640016116":{"location":[40.1894305,25.7764363],"tp":"SU","ts":"2021-04-19T10:09:01Z","tags":{"ele":"429","source":"OpenTopoMap"}},"8640021917":{"location":[40.1888404,25.781672],"tp":"SU","ts":"2021-04-19T10:09:01Z","tags":{"ele":"534","source":"OpenTopoMap"}},"8640021918":{"location":[40.1863488,25.7640981],"tp":"SU","ts":"2021-04-19T10:09:01Z","tags":{"ele":"160","source":"OpenTopoMap"}},"8640021919":{"location":[40.1805947,25.7507729],"tp":"SU","ts":"2021-04-19T10:09:01Z","tags":{"ele":"164","source":"OpenTopoMap"}},"8640021920":{"location":[40.1807095,25.756824],"tp":"SU","ts":"2021-04-19T10:09:01Z","tags":{"ele":"219","source":"OpenTopoMap"}},"8640021921":{"location":[40.185775,25.7590556],"tp":"SU","ts":"2021-04-19T10:09:01Z","tags":{"ele":"106","source":"OpenTopoMap"}},"8640021922":{"location":[40.1869389,25.7533479],"tp":"SU","ts":"2021-04-19T10:09:01Z","tags":{"ele":"87","source":"OpenTopoMap"}},"8640021923":{"location":[40.1869061,25.7455802],"tp":"SU","ts":"2024-01-25T21:42:34Z","tags":{"ele":"207","source":"OpenTopoMap"}},"8640021924":{"location":[40.1846275,25.741117],"tp":"SU","ts":"2021-04-19T10:09:01Z","tags":{"ele":"157","source":"OpenTopoMap"}},"8640021925":{"location":[40.1834308,25.7351947],"tp":"SU","ts":"2021-04-19T10:09:01Z","tags":{"ele":"194","source":"OpenTopoMap"}}}