{"356516233":{"location":[38.1106642,-81.1781615],"tp":"SU","tags":{"ele":"628","gnis:feature_id":"1537699","name":"Cotton Hill","wikidata":"Q31553912"}},"356517100":{"location":[38.1528863,-81.1151043],"tp":"SU","tags":{"ele":"774","gnis:feature_id":"1539360","name":"Gauley Mountain","wikidata":"Q31589570"}},"356524651":{"location":[38.1864967,-81.1137159],"tp":"SU","tags":{"ele":"708","gnis:feature_id":"1553824","name":"Bearwallow Knob","wikidata":"Q31494054"}},"356524690":{"location":[38.0787203,-81.1856612],"tp":"SU","tags":{"ele":"758","gnis:feature_id":"1553901","name":"Big Rock","wikidata":"Q31500177"}},"356524838":{"location":[38.1848316,-80.9842667],"tp":"SU","tags":{"ele":"647","gnis:feature_id":"1554398","name":"Emanuel Hill","wikidata":"Q31577685"}},"356524870":{"location":[38.0545539,-81.1956612],"tp":"SU","tags":{"ele":"845","gnis:feature_id":"1554483","name":"Ford Knob","wikidata":"Q31583855"}},"356524921":{"location":[38.1098318,-81.0917693],"tp":"SU","tags":{"ele":"577","gnis:feature_id":"1554660","name":"Harvey Knob","wikidata":"Q31716871"}},"356525428":{"location":[38.0648354,-80.8964845],"tp":"SU","tags":{"ele":"747","gnis:feature_id":"1556053","name":"Betty Bell Knob","wikidata":"Q31497885"}},"356536921":{"location":[38.2448301,-80.9989904],"tp":"SU","tags":{"ele":"705","gnis:feature_id":"1741208","name":"Panther Mountain","wikidata":"Q31462780"}},"11139008294":{"location":[38.0733366,-81.1274215],"tp":"SU","tags":{"ele":"678"}},"11139008295":{"location":[38.0627144,-81.1304736],"tp":"SU","tags":{"ele":"686"}}}