{"1828853119":{"location":[-18.4631507,-65.0739501],"tp":"SU","ts":"2019-05-13T13:27:11Z","tags":{"ele":"3484","name":"Cumbre Tiatino","source":"Marco Cardona Expeditions 3484 msnm"}},"3009680972":{"location":[-18.3366482,-65.3118569],"tp":"SU","ts":"2022-09-30T17:48:28Z","tags":{"name":"Albañil Punta"}},"7244081440":{"location":[-18.6402601,-65.2016804],"tp":"SU","ts":"2020-02-26T06:02:13Z","tags":{"ele":"2144","name":"Cerro Sausal"}},"7244081441":{"location":[-18.6231558,-65.2236117],"tp":"SU","ts":"2020-02-26T06:02:13Z","tags":{"ele":"2118","name":"Cerro La Barca"}}}