{"6166725753":{"location":[-5.0408438,35.8179188],"tp":"SU","tags":{"name":"1540","source":"OpenTopoMap"}},"6166725754":{"location":[-5.0720714,35.8213948],"tp":"SU","tags":{"name":"1500","source":"OpenTopoMap"}},"6166725755":{"location":[-5.0621327,35.8133912],"tp":"SU","tags":{"name":"1460","source":"OpenTopoMap"}},"6166725756":{"location":[-5.0397751,35.8030271],"tp":"SU","tags":{"name":"1410","source":"OpenTopoMap"}},"6166725757":{"location":[-5.0547372,35.7981562],"tp":"SU","tags":{"name":"1400","source":"OpenTopoMap"}},"6166725758":{"location":[-5.066322,35.7921052],"tp":"SU","tags":{"name":"1380","source":"OpenTopoMap"}}}