{"5251023306":{"location":[45.3479237,21.7978496],"tp":"SU","tags":{"ele":"422.0","name":"Ferendia"}},"5251023307":{"location":[45.3505917,21.848475],"tp":"SU","tags":{"ele":"400.3","name":"Tâlva Mare II"}},"5251023308":{"location":[45.3586791,21.8046639],"tp":"SU","tags":{"ele":"361.8","name":"Poiana Coltan"}},"5251023312":{"location":[45.3878608,21.9069582],"tp":"SU","tags":{"ele":"301.9","name":"Oprisu"}},"5251023313":{"location":[45.3889497,21.8499659],"tp":"SU","tags":{"ele":"430.2","name":"Obîrsia Magura"}},"5251023314":{"location":[45.3916418,21.9542717],"tp":"SU","tags":{"ele":"328.4","name":"Dealu Danciu"}},"7308738562":{"location":[45.3771281,22.1093805],"tp":"SU","tags":{"ele":"520","name":"Piatra de strajă","source":"survey"}},"9683315214":{"location":[45.3693532,22.1479484],"tp":"SU","tags":{"ele":"585","name":"Dealul Gleznei"}},"10567908184":{"location":[45.4629807,22.1470284],"tp":"SU","tags":{"ele":"282","name":"Dealul Bătroanei"}},"11619361460":{"location":[45.3532185,22.1078485],"tp":"SU","tags":{"ele":"704","name":"Obârșia Văii","name:ro":"Măcășel"}},"11619608531":{"location":[45.3572089,22.1351775],"tp":"SU","tags":{"ele":"632","name":"Dealul Mare","source":"Geoportal ANCPI"}},"11724648561":{"location":[45.5034986,22.0507754],"tp":"SU","tags":{"ele":"300","name":"Dealul Pietrosu"}},"11724688897":{"location":[45.5261119,22.0686752],"tp":"SU","tags":{"ele":"252","name":"Dealul Grindu"}},"11724690372":{"location":[45.4875303,22.103168],"tp":"SU","tags":{"ele":"307","name":"Dealul Caprei"}},"12433050909":{"location":[45.461969,22.121519],"tp":"SU","tags":{"ele":"302"}},"12612742056":{"location":[45.4701073,22.1421105],"tp":"SU","tags":{"ele":"282"}},"12614912908":{"location":[45.4777024,22.1398865],"tp":"SU","tags":{"ele":"315","name":"La Cântari","source":"survey"}},"12836513601":{"location":[45.4769624,22.1353865],"tp":"SU","tags":{"ele":"316"}},"13677032909":{"location":[45.3935341,22.1289572],"tp":"SU","tags":{"ele":"367","name":"Vf. Cetățeaua"}}}