{"349028469":{"location":[48.9465123,-120.8785658],"tp":"SU","tags":{"ele":"2309","gnis:feature_id":"1521447","name":"Joker Mountain","source":"USGS","wikidata":"Q49040127"}},"356544345":{"location":[48.9409695,-120.755394],"tp":"SU","tags":{"ele":"2317","gnis:feature_id":"1516656","name":"Blizzard Peak","wikidata":"Q49014241"}},"356544503":{"location":[48.9820793,-120.8617874],"tp":"SU","tags":{"ele":"2511","gnis:feature_id":"1517474","name":"Castle Peak","wikidata":"Q49018484"}},"356544970":{"location":[48.9687456,-120.8820653],"tp":"SU","tags":{"ele":"2352","gnis:feature_id":"1519783","name":"Freezeout Mountain","wikidata":"Q49030522"}},"356546468":{"location":[48.9226368,-120.7062253],"tp":"SU","tags":{"ele":"2303","gnis:feature_id":"1525993","name":"Smoky Mountain","wikidata":"Q49074930"}},"356546990":{"location":[48.9729141,-120.7673397],"tp":"SU","tags":{"ele":"2395","gnis:feature_id":"1528262","name":"Mount Winthrop","wikidata":"Q49055231"}},"1176168911":{"location":[49.0107206,-120.8375721],"tp":"SU","tags":{"ele":"2409","name":"Frosty Mountain","source":"NRCan-CanVec-7.0"}},"1176168952":{"location":[49.0435771,-120.7544161],"tp":"SU","tags":{"ele":"1843","name":"Windy Joe Mountain","source":"NRCan-CanVec-7.0"}},"1176168978":{"location":[49.0980003,-120.768142],"tp":"SU","tags":{"description":"The volcanoes themselves may have been on land, or they may have formed volcanic islands (Coates 1974). Blackwall Peak is likely one such island formed approximately 160 million years B.P. (Coates 1974). ","ele":"2063","name":"Blackwall Peak","source":"O'Brien, Jennifer Ann. Jurassic biostratigraphy and evolution of the Methow Trough, southwestern British Columbia (1987)","source_ref":"http://citeseerx.ist.psu.edu/viewdoc/download?doi=10.1.1.845.7379&rep=rep1&type=pdf","volcano:status":"extinct"}},"1176168989":{"location":[49.0854318,-120.9240951],"tp":"SU","tags":{"ele":"1889","name":"Grassy Mountain","source":"NRCan-CanVec-7.0"}},"1177346997":{"location":[49.1509318,-120.7571985],"tp":"SU","tags":{"ele":"2147","name":"Big Buck Mountain","source":"NRCan-CanVec-7.0"}},"1177383928":{"location":[49.0374059,-120.6371839],"tp":"SU","tags":{"ele":"2154","name":"Chuwanten Mountain","source":"NRCan-CanVec-7.0"}},"3740783541":{"location":[48.9929762,-120.8472749],"tp":"SU","tags":{"ele":"2223"}},"3740784028":{"location":[48.97912,-120.8542701],"tp":"SU","tags":{"ele":"2279"}},"3742021360":{"location":[48.9336774,-120.7773488],"tp":"SU","tags":{}},"3742021584":{"location":[48.9381598,-120.8650249],"tp":"SU","tags":{}},"3742021619":{"location":[48.9262919,-120.8537285],"tp":"SU","tags":{}},"3743116872":{"location":[48.9910395,-120.6968651],"tp":"SU","tags":{}},"3743117176":{"location":[48.9845481,-120.6962643],"tp":"SU","tags":{}},"3743412190":{"location":[48.9250019,-120.6836676],"tp":"SU","tags":{}},"3743412213":{"location":[48.9778588,-120.7702503],"tp":"SU","tags":{}},"3743414132":{"location":[48.9336225,-120.6812514],"tp":"SU","tags":{}},"3743414334":{"location":[48.9424876,-120.7425775],"tp":"SU","tags":{}},"3743414393":{"location":[48.971577,-120.753449],"tp":"SU","tags":{}},"3743414400":{"location":[48.9291961,-120.6978167],"tp":"SU","tags":{}},"3743414643":{"location":[48.9530511,-120.6486068],"tp":"SU","tags":{}},"3743414690":{"location":[48.9919687,-120.7815371],"tp":"SU","tags":{}},"3743414744":{"location":[48.9682302,-120.6813587],"tp":"SU","tags":{}},"3743414763":{"location":[48.9499511,-120.7266913],"tp":"SU","tags":{}},"3743414826":{"location":[48.9851396,-120.7761083],"tp":"SU","tags":{}},"3743414872":{"location":[48.949534,-120.7420625],"tp":"SU","tags":{}},"3743482520":{"location":[48.9909268,-120.6562028],"tp":"SU","tags":{}},"3743482549":{"location":[48.9913915,-120.6366978],"tp":"SU","tags":{}},"3889525045":{"location":[49.1331887,-120.8560379],"tp":"SU","tags":{"ele":"1908","name":"Mount Kelly"}},"4089072798":{"location":[49.1499744,-120.7969374],"tp":"SU","tags":{"ele":"1959"}},"4469646710":{"location":[49.0134172,-120.8481978],"tp":"SU","tags":{"ele":"2426","name":"Frosty Mountain"}},"4469659040":{"location":[49.1375848,-120.8101515],"tp":"SU","tags":{"ele":"1902","name":"Burnt Knoll"}},"5210979875":{"location":[49.0738225,-120.9368751],"tp":"SU","tags":{"ele":"1801","name":"Mara Peak"}},"5225017798":{"location":[48.9837633,-120.9169941],"tp":"SU","tags":{}},"5633817106":{"location":[49.1477521,-120.7552163],"tp":"SU","tags":{"ele":"2143"}},"12715209406":{"location":[49.1495978,-120.8692378],"tp":"SU","tags":{"ele":"1949","source":"iMap BC spot height ObjectID 1821398"}},"12715209408":{"location":[49.144394,-120.8642113],"tp":"SU","tags":{"ele":"1937","source":"iMap BC spot height ObjectID 1570573"}},"12715209409":{"location":[49.1362556,-120.8575568],"tp":"SU","tags":{"ele":"1933","source":"iMap BC spot height ObjectID 1570571 and local observation of highest point"}}}