{"26863554":{"location":[44.970989,16.9774162],"tp":"SU","ts":"2023-11-30T00:04:44Z","tags":{"ele":"977","name":"Лисина / Lisina","name:sr":"Лисина"}},"907522639":{"location":[44.980682,16.9595977],"tp":"SU","ts":"2025-04-22T10:52:09Z","tags":{"ele":"899","name":"Veliki Vis","name:sr":"Велики Вис"}},"936831131":{"location":[45.024288,16.9782802],"tp":"SU","ts":"2017-09-10T07:47:28Z","tags":{"ele":"582"}},"936856547":{"location":[45.003213,16.9807933],"tp":"SU","ts":"2021-12-10T21:29:32Z","tags":{"ele":"871","name":"Projsa","name:sr":"Пројса"}},"936856553":{"location":[45.008462,16.9793943],"tp":"SU","ts":"2017-09-10T07:47:28Z","tags":{"ele":"793"}},"936856562":{"location":[45.014356,16.9863556],"tp":"SU","ts":"2021-12-10T21:29:32Z","tags":{"ele":"644","name":"Lipovača","name:sr":"Липовача"}},"936856572":{"location":[45.016202,16.97462],"tp":"SU","ts":"2017-09-10T07:47:28Z","tags":{"ele":"653"}},"936980632":{"location":[45.0138484,16.9091487],"tp":"SU","ts":"2023-12-03T16:54:07Z","tags":{"ele":"804","name":"Mrakovica","name:sr":"Мраковица","wikidata":"Q12755774"}},"3888808847":{"location":[44.9629079,17.0553941],"tp":"SU","ts":"2021-12-10T21:29:32Z","tags":{"ele":"841","name":"Gugunova glava","name:sr":"Гугунова глава"}},"4130749249":{"location":[45.0083559,16.8950186],"tp":"SU","ts":"2021-12-10T21:29:32Z","tags":{"ele":"691","name":"Мијаков клин","name:sr":"Мијаков клин","name:sr-Latn":"Mijakov klin"}},"4166948910":{"location":[44.9656523,16.9634028],"tp":"SU","ts":"2020-09-11T02:31:56Z","tags":{"ele":"899","name":"Главица / Glavica","name:sr":"Главица"}},"5948130275":{"location":[44.8618559,16.9427],"tp":"SU","ts":"2021-12-10T21:29:32Z","tags":{"ele":"202","name":"Zemunica","name:sr":"Земуница"}},"7021716859":{"location":[45.0016948,16.8785621],"tp":"SU","ts":"2021-04-28T21:06:12Z","tags":{"ele":"667","name":"Bijeli kamen","name:sr":"Бијели камен"}},"7021716860":{"location":[45.0192213,16.8849929],"tp":"SU","ts":"2021-12-10T21:29:32Z","tags":{"ele":"793","name":"Главуша","name:sr":"Главуша"}},"7179725043":{"location":[44.8404169,17.0782073],"tp":"SU","ts":"2021-12-10T21:29:32Z","tags":{"ele":"433","name":"Klupe","name:sr":"Клупе"}},"8925138289":{"location":[44.9553994,17.0752215],"tp":"SU","ts":"2021-12-10T21:29:32Z","tags":{"ele":"702","name":"Kamenito brdo","name:sr":"Каменито брдо"}},"8925138311":{"location":[44.9359246,17.1788476],"tp":"SU","ts":"2023-07-14T11:02:44Z","tags":{"ele":"438","name":"Krndija","name:sr":"Крндија"}},"8925155829":{"location":[44.9231761,17.1752679],"tp":"SU","ts":"2021-12-10T21:29:32Z","tags":{"ele":"381","name":"Visoka glava","name:sr":"Висока глава"}},"8925155848":{"location":[44.9322685,17.1409786],"tp":"SU","ts":"2021-12-10T21:29:32Z","tags":{"ele":"408","name":"Vis","name:sr":"Вис"}},"8925155850":{"location":[44.936218,17.1281147],"tp":"SU","ts":"2021-12-10T21:29:32Z","tags":{"ele":"437","name":"Grgina glava","name:sr":"Гргина глава"}},"8925155867":{"location":[44.943782,17.1422338],"tp":"SU","ts":"2021-12-10T21:29:32Z","tags":{"ele":"510","name":"Čuka","name:sr":"Чука"}},"8925155868":{"location":[44.9491582,17.1252608],"tp":"SU","ts":"2021-12-10T21:29:32Z","tags":{"ele":"520","name":"Cerova glava","name:sr":"Церова глава"}},"8925155913":{"location":[44.9555968,17.0907569],"tp":"SU","ts":"2021-12-10T21:29:32Z","tags":{"ele":"684","name":"Karaula","name:sr":"Караула"}},"8925155914":{"location":[44.9534557,17.1140385],"tp":"SU","ts":"2021-12-10T21:29:32Z","tags":{"ele":"596","name":"Lisina","name:sr":"Лисина"}},"10062543398":{"location":[45.0297864,16.9241917],"tp":"SU","ts":"2023-11-30T23:17:34Z","tags":{"ele":"710","name":"Slatinska glava","name:sr":"Слатинска глава"}},"10864218631":{"location":[45.0181232,17.0310635],"tp":"SU","ts":"2023-11-30T23:40:18Z","tags":{"ele":"644","name":"Gig","name:sr":"Гиг"}},"12320358507":{"location":[45.0053392,17.1702825],"tp":"SU","ts":"2024-11-07T11:14:20Z","tags":{"ele":"267","name":"Popisanac"}},"12541078331":{"location":[44.9825047,16.9389212],"tp":"SU","ts":"2025-01-29T07:47:52Z","tags":{"ele":"876","name":"Gola Planina"}}}