{"357557257":{"location":[43.3653473,-76.0179754],"tp":"SU","tags":{"ele":"201","gnis:feature_id":"948856","name":"Dutch Hill"}},"357569027":{"location":[43.5217369,-75.9651962],"tp":"SU","tags":{"ele":"219","gnis:feature_id":"955293","name":"Lighthouse Hill"}},"357572813":{"location":[43.5706253,-75.9701967],"tp":"SU","tags":{"ele":"340","gnis:feature_id":"958230","name":"Myers Hill"}},"357576319":{"location":[43.3597918,-75.9607508],"tp":"SU","tags":{"ele":"211","gnis:feature_id":"959973","name":"Patchen Hill"}},"357596323":{"location":[43.4459026,-76.2702082],"tp":"SU","tags":{"ele":"144","gnis:feature_id":"970391","name":"Mullen Hill"}}}