{"618029610":{"location":[4.488611,-76.261667],"tp":"SU","tags":{"name":"Loma Puerte"}},"618029624":{"location":[4.342778,-76.191111],"tp":"SU","tags":{"name":"Cerro Cesteadero"}},"618029631":{"location":[4.293611,-76.218889],"tp":"SU","tags":{"name":"Loma de Los Pozos"}},"618029648":{"location":[4.228056,-76.270556],"tp":"SU","tags":{"name":"Loma Calabaza"}},"703513268":{"location":[4.5316184,-76.2673475],"tp":"SU","tags":{"divipola":"76250","fixme":"Revisar: este punto fue creado por importación directa","is_in":"Colombia; Valle ; El Dovio","name":"Cerro Paramillo","note":"OROGRAFIA, MONTAÑAS Y CERROS, 00ec25546ef2b00765c80fe4ad0af496","source":"OCHA Colombia 2010"}},"7773819735":{"location":[4.5220983,-76.0899403],"tp":"SU","tags":{}}}