{"703218195":{"location":[3.3376349,-75.9893673],"tp":"SU","tags":{"divipola":"73616","ele":"4055","is_in":"Colombia; Tolima ; Rioblanco","name":"Cuchilla Peña Negra","note":"OROGRAFIA, MONTAÑAS Y CERROS, 9dd2099c377e23c9e4ff7f323c0b5194","source":"OCHA Colombia 2010"}},"703218198":{"location":[3.3331446,-75.9555453],"tp":"SU","tags":{"divipola":"73616","fixme":"Revisar: este punto fue creado por importación directa","is_in":"Colombia; Tolima ; Rioblanco","name":"Cuchilla El Purgatorio","note":"OROGRAFIA, MONTAÑAS Y CERROS, 88273be0fc1b38dfd2762f81a20bea2b","source":"OCHA Colombia 2010"}},"703218203":{"location":[3.3109989,-75.9418437],"tp":"SU","tags":{"divipola":"73616","fixme":"Revisar: este punto fue creado por importación directa","is_in":"Colombia; Tolima ; Rioblanco","name":"Cuchilla Bejucueros","note":"OROGRAFIA, MONTAÑAS Y CERROS, bb62ef78f793ad061ad67a1776c7da0f","source":"OCHA Colombia 2010"}},"703218211":{"location":[3.3854147,-75.9773086],"tp":"SU","tags":{"divipola":"73616","fixme":"Revisar: este punto fue creado por importación directa","is_in":"Colombia; Tolima ; Rioblanco","name":"Cuchilla Las Pavas","note":"OROGRAFIA, MONTAÑAS Y CERROS, 3d5d760df6189e295c10a23cc1dfa49f","source":"OCHA Colombia 2010"}},"703218212":{"location":[3.3472189,-75.9709691],"tp":"SU","tags":{"divipola":"73616","ele":"4065","fixme":"Revisar: este punto fue creado por importación directa","is_in":"Colombia; Tolima ; Rioblanco","name":"Cuchilla El Triunfo","note":"OROGRAFIA, MONTAÑAS Y CERROS, dc357502f8c8fa59e4265ed31e5fd1ae","source":"OCHA Colombia 2010"}},"703218213":{"location":[3.4551126,-75.9586065],"tp":"SU","tags":{"divipola":"73616","ele":"3815","is_in":"Colombia; Tolima ; Rioblanco","name":"Cuchilla La Reina","source":"OCHA Colombia 2010"}},"703218214":{"location":[3.482164,-75.9624863],"tp":"SU","tags":{"divipola":"73616","fixme":"Revisar: este punto fue creado por importación directa","is_in":"Colombia; Tolima ; Rioblanco","name":"Cuchilla De La Lejia","note":"OROGRAFIA, MONTAÑAS Y CERROS, 661f5e1f536ffc7734e7dae36395133d","source":"OCHA Colombia 2010"}},"703218216":{"location":[3.351548,-75.9567914],"tp":"SU","tags":{"divipola":"73616","ele":"4062","is_in":"Colombia; Tolima ; Rioblanco","name":"Filo Del Serrucho","note":"OROGRAFIA, MONTAÑAS Y CERROS, 54c045a6d5cb3436e254c44b7492523f","source":"OCHA Colombia 2010"}},"703218218":{"location":[3.4616145,-75.9911122],"tp":"SU","tags":{"divipola":"73616","fixme":"Revisar: este punto fue creado por importación directa","is_in":"Colombia; Tolima ; Rioblanco","name":"Cuchilla La Reina","note":"OROGRAFIA, MONTAÑAS Y CERROS, ccd97d21340c7c4f8716a44eff842fc2","source":"OCHA Colombia 2010"}},"703512838":{"location":[3.4691761,-76.0716375],"tp":"SU","tags":{"divipola":"76563","ele":"4090","is_in":"Colombia; Valle ; Pradera","name":"Cuchilla San Pedro","note":"OROGRAFIA, MONTAÑAS Y CERROS, e5c1d0313819b6bbee5df2931c722c0f","source":"OCHA Colombia 2010"}},"4810330608":{"location":[3.4925659,-75.9992389],"tp":"SU","tags":{"ele":"4240","name":"Cerro"}},"4819224799":{"location":[3.434395,-75.9752541],"tp":"SU","tags":{"ele":"3842","name":"Cerro San Jorge"}},"4821462697":{"location":[3.2660937,-76.0623074],"tp":"SU","tags":{"ele":"4150","name":"P."}},"4821462698":{"location":[3.297491,-76.0708529],"tp":"SU","tags":{"ele":"4122","name":"P."}},"4821462707":{"location":[3.3271308,-76.0575438],"tp":"SU","tags":{"ele":"4284","name":"Cerro de las Lágrimas"}},"4821462709":{"location":[3.3366392,-76.0485637],"tp":"SU","tags":{"name":"P. 4.155"}},"4821465024":{"location":[3.4658342,-76.0293752],"tp":"SU","tags":{"name":"P. 4.225"}},"4821511992":{"location":[3.199962,-76.0904825],"tp":"SU","tags":{"ele":"4176","name":"P."}},"4821512217":{"location":[3.2189273,-76.0485801],"tp":"SU","tags":{"ele":"4100","name":"P."}},"4821512746":{"location":[3.2324976,-76.0825186],"tp":"SU","tags":{"ele":"4141","name":"P."}},"4821524256":{"location":[3.5039104,-76.0269839],"tp":"SU","tags":{"ele":"4169","name":"P."}},"4821524257":{"location":[3.351306,-76.0620431],"tp":"SU","tags":{"ele":"4165","name":"P."}},"4821524258":{"location":[3.3683088,-76.0211179],"tp":"SU","tags":{"ele":"3970","name":"Peña El Águila"}},"4825741086":{"location":[3.4594357,-76.047082],"tp":"SU","tags":{"ele":"4155","name":"Pico","source":"SRTM"}}}