{"1237538166":{"location":[27.614534,41.876859],"tp":"SU","ts":"2022-11-13T06:40:53Z","tags":{"GNS:dsg_code":"HLLS","GNS:dsg_name":"hills","GNS:id":"194052","int_name":"Ḩuzūm Haffāfāt","name":"حزوم هفافات","name:ar":"حزوم هفافات","name:de":"Huzum Haffafat","name:en":"Huzum Haffafat","name:fr":"Huzum Haffafat","source:name":"GNS"}},"1237538865":{"location":[27.579216,41.854138],"tp":"SU","ts":"2022-11-13T06:40:53Z","tags":{"GNS:dsg_code":"HLL","GNS:dsg_name":"hill","GNS:id":"194051","int_name":"Qārat aş Şandūq","name":"قارة الصندوق","name:ar":"قارة الصندوق","name:de":"Qarat as Sanduq","name:en":"Qarat as Sanduq","name:fr":"Qarat as Sanduq","source:name":"GNS"}},"1237538871":{"location":[27.5550052,42.1198071],"tp":"SU","ts":"2023-12-04T14:03:14Z","tags":{"GNS:dsg_code":"HLL","GNS:dsg_name":"hill","GNS:id":"198372","int_name":"Ḩazm al ‘Arād","name":"حزم العراد","name:ar":"حزم العراد","name:de":"Hazm al `Arad","name:en":"Hazm al `Arad","name:fr":"Hazm al `Arad","source:name":"GNS"}},"1237538887":{"location":[27.5641511,41.9435759],"tp":"SU","ts":"2023-12-04T14:04:37Z","tags":{"GNS:dsg_code":"HLLS","GNS:dsg_name":"hills","GNS:id":"194041","int_name":"Ḩuzūm aş Şumakhāt","name":"حزوم الصمخات","name:ar":"حزوم الصمخات","name:de":"Huzum as Sumakhat","name:en":"Huzum as Sumakhat","name:fr":"Huzum as Sumakhat","source:name":"GNS"}},"1237556757":{"location":[27.506288,41.883555],"tp":"SU","ts":"2022-11-13T06:40:53Z","tags":{"GNS:dsg_code":"HLLS","GNS:dsg_name":"hills","GNS:id":"194023","int_name":"Ḩumr al Qaltah","name":"حمر القلتة","name:ar":"حمر القلتة","name:de":"Humr al Qaltah","name:en":"Humr al Qaltah","name:fr":"Humr al Qaltah","source:name":"GNS"}},"1237556827":{"location":[27.494845,41.925967],"tp":"SU","ts":"2022-11-13T06:40:53Z","tags":{"GNS:dsg_code":"HLLS","GNS:dsg_name":"hills","GNS:id":"194010","int_name":"Jibāl ‘Akkāsh","name":"جبال عكاش","name:ar":"جبال عكاش","name:de":"Jibal `Akkash","name:en":"Jibal `Akkash","name:fr":"Jibal `Akkash","source:name":"GNS"}},"1237557269":{"location":[27.456565,42.040915],"tp":"SU","ts":"2022-11-13T06:40:53Z","tags":{"GNS:dsg_code":"HLL","GNS:dsg_name":"hill","GNS:id":"198440","int_name":"Hiḑāb al Milīḩīyāt","name":"هضاب المليحيات","name:ar":"هضاب المليحيات","name:de":"Hidab al Milihiyat","name:en":"Hidab al Milihiyat","name:fr":"Hidab al Milihiyat","source:name":"GNS"}},"1237557319":{"location":[27.433537,42.014242],"tp":"SU","ts":"2022-11-13T06:40:53Z","tags":{"GNS:dsg_code":"HLL","GNS:dsg_name":"hill","GNS:id":"198447","int_name":"Hiḑāb Quşaymīl","name":"هضاب قصيميل","name:ar":"هضاب قصيميل","name:de":"Hidab Qusaymil","name:en":"Hidab Qusaymil","name:fr":"Hidab Qusaymil","source:name":"GNS"}},"1237557413":{"location":[27.419932,41.982956],"tp":"SU","ts":"2022-11-13T06:40:53Z","tags":{"GNS:dsg_code":"HLLS","GNS:dsg_name":"hills","GNS:id":"193991","int_name":"Jibāl al Milīḩīyah","name":"جبال المليحية","name:ar":"جبال المليحية","name:de":"Jibal al Milihiyah","name:en":"Jibal al Milihiyah","name:fr":"Jibal al Milihiyah","source:name":"GNS"}},"1237557592":{"location":[27.389539,42.100647],"tp":"SU","ts":"2022-11-13T06:40:53Z","tags":{"GNS:dsg_code":"HLL","GNS:dsg_name":"hill","GNS:id":"193782","int_name":"Jabal Şabḩā","name":"جبل صبحا","name:ar":"جبل صبحا","name:de":"Jabal Sabha","name:en":"Jabal Sabha","name:fr":"Jabal Sabha","source:name":"GNS"}},"1237558394":{"location":[27.52202,41.952019],"tp":"SU","ts":"2022-11-13T06:40:53Z","tags":{"GNS:dsg_code":"HLLS","GNS:dsg_name":"hills","GNS:id":"194026","int_name":"Ḩumr Yāţib","name":"حمر ياطب","name:ar":"حمر ياطب","name:de":"Humr Yatib","name:en":"Humr Yatib","name:fr":"Humr Yatib","source:name":"GNS"}},"9823410104":{"location":[27.5659195,41.9125621],"tp":"SU","ts":"2022-06-16T19:10:55Z","tags":{"name":"ذرَيريَّات"}},"11247470832":{"location":[27.490047,41.9782448],"tp":"SU","ts":"2023-10-08T05:29:50Z","tags":{"name":"جبل ياطب"}},"11247470833":{"location":[27.4800628,41.9877291],"tp":"SU","ts":"2023-10-08T05:29:50Z","tags":{"name":"جبل الدنان"}},"11870951034":{"location":[27.4612653,41.9370514],"tp":"SU","ts":"2024-05-01T06:30:11Z","tags":{"alt_name":"Jabal Şa‘nab","name":"جبل صعنب","name:ar":"جبل صعنب","name:en":"Jabal Sa`nab","source":"GNS"}},"11871652347":{"location":[27.3747533,41.8778429],"tp":"SU","ts":"2024-05-01T11:53:42Z","tags":{"alt_name":"Jibāl Mu‘allaq","alt_name:ar":"جبال معلّق","name":"جبال المعلق","name:ar":"جبال المعلق","name:en":"Jibal Mu`allaq","source":"GNS"}}}