{"3559946886":{"location":[33.274369,132.5381962],"tp":"SU","tags":{"ele":"130","name":"犬尾山","name:ja_rm":"Inubi-Yama","source":"GSImaps/std"}},"3584908827":{"location":[33.2870929,132.5385126],"tp":"SU","tags":{"alt_name":"石城","ele":"121.5","name":"御殿山","source":"GSImaps/std"}},"5832061619":{"location":[33.4200974,132.5330961],"tp":"SU","tags":{}},"7908398387":{"location":[33.4312533,132.4823713],"tp":"SU","tags":{"ele":"645.5","name":"大畑山"}},"7912764110":{"location":[33.3654084,132.4528026],"tp":"SU","tags":{"ele":"593.4","name":"堂所山"}}}