{"576036069":{"location":[40.3401052,-0.5040866],"tp":"SU","tags":{"ele":"1752"}},"948743731":{"location":[40.3188014,-0.6764899],"tp":"SU","tags":{"ele":"1807.50","name":"Bandera","wikidata":"Q115499596"}},"948786849":{"location":[40.3460785,-0.3754408],"tp":"SU","tags":{"ele":"1501.00","name":"Gayo","wikidata":"Q115503789"}},"948811410":{"location":[40.3677014,-0.4894943],"tp":"SU","tags":{"ele":"1740.50","name":"Puntal del Mas del Vicario","wikidata":"Q115508584"}},"948814723":{"location":[40.3305072,-0.5322763],"tp":"SU","tags":{"ele":"1781.80","name":"La Cespedosa","wikidata":"Q115501739"}},"975664325":{"location":[40.2562713,-0.3788812],"tp":"SU","tags":{"alt_name":"Tossal del Carrascalet","ele":"1452","name":"Tossal de Càndida","name:ca":"Tossal de Càndida"}},"1242987163":{"location":[40.4257254,-0.4359995],"tp":"SU","tags":{"ele":"1555","name":"Loma la Rosca"}},"1242988352":{"location":[40.3717024,-0.4297161],"tp":"SU","tags":{"ele":"1591","loc_name":"Escorchaboyes","name":"Escorchabueyes"}},"1242993486":{"location":[40.2184041,-0.6812107],"tp":"SU","tags":{"ele":"1214","name":"Alto del Castillo","source":"Instituto Geográfico Nacional","source:date":"201011","source:name":"Nomenclator Geográfico Básico de España"}},"1242993780":{"location":[40.299777,-0.6722352],"tp":"SU","tags":{"ele":"1664","name":"Alto de Sancho","source":"Instituto Geográfico Nacional","source:name":"Nomenclator Geográfico Básico de España"}},"1242994484":{"location":[40.2455192,-0.6230711],"tp":"SU","tags":{"ele":"1344","name":"Loma del Hocino","source":"Instituto Geográfico Nacional","source:date":"201011","source:name":"Nomenclator Geográfico Básico de España"}},"1242997687":{"location":[40.271273,-0.4759446],"tp":"SU","tags":{"ele":"1526","name":"Peña del Palo","source":"Instituto Geográfico Nacional","source:date":"201011","source:name":"Nomenclator Geográfico Básico de España"}},"1242997805":{"location":[40.2419407,-0.6290066],"tp":"SU","tags":{"ele":"1313","name":"El Cerrito","source":"Instituto Geográfico Nacional","source:date":"201011","source:name":"Nomenclator Geográfico Básico de España"}},"1243004558":{"location":[40.4343453,-0.6969008],"tp":"SU","tags":{"ele":"1726","name":"Cerro de Rosa María","source":"Instituto Geográfico Nacional","source:date":"201011","source:name":"Nomenclator Geográfico Básico de España"}},"1243015113":{"location":[40.4034629,-0.4142109],"tp":"SU","tags":{"ele":"1606","name":"Cabecico del Mas de Simón","source":"Instituto Geográfico Nacional"}},"1243017730":{"location":[40.4365228,-0.4913364],"tp":"SU","tags":{"ele":"1684","name":"Alto de Roda","source":"Instituto Geográfico Nacional","source:name":"Nomenclator Geográfico Básico de España"}},"1243018435":{"location":[40.415762,-0.6807286],"tp":"SU","tags":{"ele":"1703","name":"El Cerro","source":"Instituto Geográfico Nacional","source:date":"201011","source:name":"Nomenclator Geográfico Básico de España"}},"1243018652":{"location":[40.1850752,-0.671026],"tp":"SU","tags":{"ele":"1022","name":"Alto de la Venta","source":"Instituto Geográfico Nacional","source:date":"201011","source:name":"Nomenclator Geográfico Básico de España"}},"1243019063":{"location":[40.3130105,-0.5745264],"tp":"SU","tags":{"ele":"1524","name":"Cerro Brun"}},"1243020897":{"location":[40.2234935,-0.6226153],"tp":"SU","tags":{"ele":"1232","name":"Alto de la Buitrera","source":"Instituto Geográfico Nacional","source:name":"Nomenclator Geográfico Básico de España"}},"1243021474":{"location":[40.2191124,-0.6348701],"tp":"SU","tags":{"ele":"1192","name":"Cabezo Royal","source":"Instituto Geográfico Nacional","source:date":"201011","source:name":"Nomenclator Geográfico Básico de España"}},"1243024162":{"location":[40.1829483,-0.6607768],"tp":"SU","tags":{"ele":"1061","name":"Punta del Pinar","source":"Instituto Geográfico Nacional","source:date":"201011","source:name":"Nomenclator Geográfico Básico de España"}},"1243024235":{"location":[40.2600916,-0.647327],"tp":"SU","tags":{"ele":"1566","name":"Pico Artigas","source":"Instituto Geográfico Nacional","source:date":"201011","source:name":"Nomenclator Geográfico Básico de España"}},"1243237446":{"location":[40.2940115,-0.385018],"tp":"SU","tags":{"ele":"1374","loc_name":"Lloma del Mas de Monçó","name":"Lloma del Mas de Montsó"}},"1243241181":{"location":[40.2308951,-0.5383747],"tp":"SU","tags":{"ele":"1482","name":"Canto de la Ereta","official_name":"La Torre Alta"}},"1243272117":{"location":[40.2285947,-0.5146767],"tp":"SU","tags":{"ele":"1484","name":"Las Moletas","source":"Acadèmia Valenciana de la Llengua"}},"1243274355":{"location":[40.2280894,-0.4854017],"tp":"SU","tags":{"ele":"1391","name":"Cinglo de Caldereros"}},"1243278018":{"location":[40.2336856,-0.5340338],"tp":"SU","tags":{"ele":"1554","name":"La Ereta","official_name":"Las Herrerías","source":"Acadèmia Valenciana de la Llengua"}},"1249947296":{"location":[40.2333646,-0.5020275],"tp":"SU","tags":{"ele":"1505","name":"Tavas","name:ca":"Taves","name:es":"Tavas","official_name":"Alto de Tabas"}},"1249954039":{"location":[40.2640586,-0.3833859],"tp":"SU","tags":{"ele":"1649"}},"1249957983":{"location":[40.2385227,-0.5321907],"tp":"SU","tags":{"ele":"1639","name":"La Cruz del Herrero","official_name":"Alto de la Hambrienta","source:name":"Acadèmia Valenciana de la Llengua"}},"1260540561":{"location":[40.282886,-0.6024071],"tp":"SU","tags":{"ele":"1806","name":"Alto de la Cervera","source":"Instituto Geográfico Nacional","source:date":"201011","source:name":"Nomenclator Geográfico Básico de España"}},"1260540731":{"location":[40.2950317,-0.673058],"tp":"SU","tags":{"ele":"1664","name":"Alto del Hontanar","source":"Instituto Geográfico Nacional","source:date":"201011","source:name":"Nomenclator Geográfico Básico de España"}},"1260540980":{"location":[40.4391505,-0.5345184],"tp":"SU","tags":{"ele":"1862","name":"Canto Raso"}},"1260541608":{"location":[40.2751135,-0.4829],"tp":"SU","tags":{"ele":"1608","name":"El Pelejero","official_name":"Alto del Pellejero"}},"1260541660":{"location":[40.4421116,-0.4789505],"tp":"SU","tags":{"ele":"1717","name":"Pinos Claros"}},"1260543081":{"location":[40.2983888,-0.6470952],"tp":"SU","tags":{"ele":"1692","name":"Cerro de la Tea"}},"1260544041":{"location":[40.3053304,-0.6275225],"tp":"SU","tags":{"ele":"1659","name":"Alto de la Roya"}},"1260544539":{"location":[40.2801322,-0.4929109],"tp":"SU","tags":{"ele":"1564","name":"Alto de Cate","source":"Instituto Geográfico Nacional","source:date":"201011","source:name":"Nomenclator Geográfico Básico de España"}},"1260544560":{"location":[40.3656785,-0.6084713],"tp":"SU","tags":{"ele":"1957","name":"Alto del Monegro","source":"Instituto Geográfico Nacional","source:date":"201011","source:name":"Nomenclator Geográfico Básico de España"}},"1260545451":{"location":[40.429825,-0.6049185],"tp":"SU","tags":{"ele":"1977","name":"Alto de la Nave","source":"Instituto Geográfico Nacional","source:date":"201011","source:name":"Nomenclator Geográfico Básico de España"}},"1260545636":{"location":[40.3324684,-0.5964148],"tp":"SU","tags":{"ele":"1636","name":"Alto del Cerezal","source":"Instituto Geográfico Nacional","source:date":"201011","source:name":"Nomenclator Geográfico Básico de España"}},"1260547754":{"location":[40.2951783,-0.5861439],"tp":"SU","tags":{"ele":"1722","name":"Cerro Antona"}},"1260547993":{"location":[40.4102991,-0.5952363],"tp":"SU","tags":{"ele":"2001","name":"Alto del Hornillo","source":"Instituto Geográfico Nacional","source:date":"201011","source:name":"Nomenclator Geográfico Básico de España"}},"1260550157":{"location":[40.325079,-0.5513708],"tp":"SU","tags":{"ele":"1705","name":"Alto de la Erizosa","source":"Instituto Geográfico Nacional","source:date":"201011","source:name":"Nomenclator Geográfico Básico de España"}},"1260550181":{"location":[40.4461728,-0.6123976],"tp":"SU","tags":{"ele":"1912","name":"La Zaragozana","source":"Instituto Geográfico Nacional","source:date":"201011","source:name":"Nomenclator Geográfico Básico de España"}},"1260552458":{"location":[40.3169754,-0.6686026],"tp":"SU","tags":{"ele":"1802","name":"Alto del Chaparroso","source":"Instituto Geográfico Nacional","source:date":"201011","source:name":"Nomenclator Geográfico Básico de España"}},"1260554975":{"location":[40.2735229,-0.6229168],"tp":"SU","tags":{"ele":"1771","name":"Alto de la Nevera","source":"Instituto Geográfico Nacional","source:date":"201011","source:name":"Nomenclator Geográfico Básico de España"}},"1260556328":{"location":[40.2652569,-0.5644141],"tp":"SU","tags":{"ele":"1769","name":"Alto Férriz","source":"Instituto Geográfico Nacional","source:date":"201011","source:name":"Nomenclator Geográfico Básico de España"}},"2624205123":{"location":[40.341518,-0.4271185],"tp":"SU","tags":{"ele":"1554"}},"2624205145":{"location":[40.3584075,-0.4613145],"tp":"SU","tags":{"ele":"1600"}},"2624205164":{"location":[40.3608638,-0.4409273],"tp":"SU","tags":{"ele":"1526","name":"San Antonio"}},"2624205281":{"location":[40.3700665,-0.4573777],"tp":"SU","tags":{"ele":"1672","name":"La Redonda"}},"2625049933":{"location":[40.361021,-0.393088],"tp":"SU","tags":{"ele":"1297","name":"El Castillo"}},"3445418073":{"location":[40.3890142,-0.6505957],"tp":"SU","tags":{"ele":"1951","name":"Alto de la Gitana"}},"3896918065":{"location":[40.2501511,-0.5737522],"tp":"SU","tags":{"ele":"1641","name":"Peñacalva"}},"3896918066":{"location":[40.2628724,-0.5674181],"tp":"SU","tags":{"ele":"1772","name":"Férriz"}},"3907149544":{"location":[40.3200636,-0.4336862],"tp":"SU","tags":{"ele":"1524","name":"Loma del Portillo"}},"3907174103":{"location":[40.3095125,-0.4331446],"tp":"SU","tags":{"ele":"1598","name":"Muela de l'Hontanal"}},"3907183893":{"location":[40.3514384,-0.3619139],"tp":"SU","tags":{"ele":"1474","name":"Torre Halcón"}},"4775357405":{"location":[40.3607868,-0.6625485],"tp":"SU","tags":{"ele":"1781","name":"La Mazorra"}},"4775362631":{"location":[40.3982305,-0.6350834],"tp":"SU","tags":{"ele":"1912","name":"El Morrón"}},"4775368168":{"location":[40.3610157,-0.6434512],"tp":"SU","tags":{"ele":"1879","name":"La Atalayuela"}},"6213314178":{"location":[40.2517886,-0.4318863],"tp":"SU","tags":{"ele":"1519","name":"La Golosilla"}},"6346867975":{"location":[40.4094524,-0.6915815],"tp":"SU","tags":{"ele":"1731"}},"6346868289":{"location":[40.4002285,-0.6832882],"tp":"SU","tags":{"ele":"1906"}},"6349449375":{"location":[40.2984399,-0.6972688],"tp":"SU","tags":{"ele":"1359"}},"6349449377":{"location":[40.3013067,-0.6952909],"tp":"SU","tags":{"ele":"1346"}},"6349449378":{"location":[40.3027026,-0.6978105],"tp":"SU","tags":{"ele":"1382"}},"6349543760":{"location":[40.3129116,-0.6593531],"tp":"SU","tags":{"ele":"1761","name":"Peña del Rayo"}},"6349571267":{"location":[40.3470505,-0.7021903],"tp":"SU","tags":{"ele":"1547"}},"6349571272":{"location":[40.3398595,-0.7007442],"tp":"SU","tags":{"ele":"1621"}},"6349579158":{"location":[40.3448036,-0.6948236],"tp":"SU","tags":{"ele":"1574","name":"El Cerro"}},"6349579159":{"location":[40.3481499,-0.6979331],"tp":"SU","tags":{"ele":"1556"}},"6349591499":{"location":[40.3555409,-0.673963],"tp":"SU","tags":{"ele":"1611"}},"6350155798":{"location":[40.3184139,-0.6916632],"tp":"SU","tags":{"ele":"1503"}},"6350155810":{"location":[40.3175715,-0.6846978],"tp":"SU","tags":{"ele":"1644"}},"6350164433":{"location":[40.3230214,-0.6821246],"tp":"SU","tags":{"ele":"1712"}},"6350164435":{"location":[40.316647,-0.6749357],"tp":"SU","tags":{"ele":"1791"}},"6350164436":{"location":[40.3241441,-0.6884923],"tp":"SU","tags":{"ele":"1629"}},"6350173386":{"location":[40.3296364,-0.6905763],"tp":"SU","tags":{"ele":"1652"}},"6350173388":{"location":[40.3353938,-0.6918178],"tp":"SU","tags":{"ele":"1641","name":"Loma del Cerro"}},"6360027693":{"location":[40.3716461,-0.6765373],"tp":"SU","tags":{"ele":"1599"}},"6360027694":{"location":[40.3702318,-0.6728291],"tp":"SU","tags":{"ele":"1627"}},"6360031259":{"location":[40.3732398,-0.7013348],"tp":"SU","tags":{"ele":"1444"}},"6360363733":{"location":[40.3670252,-0.7019381],"tp":"SU","tags":{"ele":"1448","name":"El Cerrito"}},"7951827859":{"location":[40.2059621,-0.3595264],"tp":"SU","tags":{"ele":"1431","name":"Moleta de la Clocha"}},"7960825320":{"location":[40.2010321,-0.3671433],"tp":"SU","tags":{"ele":"1220","name":"Tozal del Montudillo"}},"8086296336":{"location":[40.2778927,-0.5567086],"tp":"SU","tags":{"ele":"1656","name":"Alto de Ramón"}},"8086296337":{"location":[40.2726131,-0.5025923],"tp":"SU","tags":{"alt_name":"Cabezo el Escobero","ele":"1312","name":"Cabezo de las Juncosas"}},"8086296338":{"location":[40.2665471,-0.5432439],"tp":"SU","tags":{"ele":"1497","name":"Peña de la Hiedra"}},"8086296339":{"location":[40.2861163,-0.5382603],"tp":"SU","tags":{"ele":"1472","name":"El Coscojoso"}},"8086375965":{"location":[40.2302666,-0.6500334],"tp":"SU","tags":{"ele":"1277","name":"La Muela"}},"8090560362":{"location":[40.3540215,-0.6236565],"tp":"SU","tags":{"ele":"1854","name":"Las Tablas"}},"8090560363":{"location":[40.3456999,-0.5943239],"tp":"SU","tags":{"ele":"1804","name":"Loma el Candialar","not:name":"El Candelar"}},"8090560364":{"location":[40.3977673,-0.5094963],"tp":"SU","tags":{"alt_name":"Cerro Pinar del Ciego","ele":"1883","name":"Bramaderas"}},"9117004587":{"location":[40.3793308,-0.6301099],"tp":"SU","tags":{"ele":"1985"}},"9117115986":{"location":[40.3817892,-0.6375065],"tp":"SU","tags":{"ele":"1995"}},"9441809635":{"location":[40.2402014,-0.361806],"tp":"SU","tags":{"ele":"1506","name":"el Morronet Roig"}},"10652722292":{"location":[40.3049286,-0.3689652],"tp":"SU","tags":{"ele":"1140","name":"el Castellet"}},"10719842704":{"location":[40.252104,-0.4054545],"tp":"SU","tags":{"ele":"1532","name":"Los Torrojones"}},"10719853905":{"location":[40.2561099,-0.3866796],"tp":"SU","tags":{"ele":"1533","name":"Tozal de Maluendas"}},"10719853906":{"location":[40.2741846,-0.3844238],"tp":"SU","tags":{"ele":"1594","name":"el Xaparral","name:ca":"el Xaparral"}},"10719853907":{"location":[40.2838934,-0.3784845],"tp":"SU","tags":{"alt_name":"Tossal de la Batalla","ele":"1511","loc_name":"Tossal del Mas de Monçó","name":"Tossal del Mas de Montsó"}},"10722069063":{"location":[40.2542739,-0.4432964],"tp":"SU","tags":{"ele":"1512"}},"10724255801":{"location":[40.3226955,-0.5142858],"tp":"SU","tags":{"ele":"1723","name":"Cerro de Torre Quemada"}},"10724255802":{"location":[40.3004751,-0.4598076],"tp":"SU","tags":{"ele":"1723"}},"10724255804":{"location":[40.3073527,-0.4726568],"tp":"SU","tags":{"ele":"1705","name":"Monrial"}},"10724304005":{"location":[40.3079585,-0.4786319],"tp":"SU","tags":{"ele":"1689","name":"Peñarrero"}},"10724304007":{"location":[40.2996683,-0.4467588],"tp":"SU","tags":{"ele":"1664"}},"10724304008":{"location":[40.3001644,-0.4388474],"tp":"SU","tags":{"ele":"1654"}},"10724304009":{"location":[40.3030453,-0.4984034],"tp":"SU","tags":{"ele":"1508","name":"Loma Rasa"}},"10724304010":{"location":[40.3105071,-0.5015148],"tp":"SU","tags":{"ele":"1509","name":"Tozal Royo"}},"10753185457":{"location":[40.3069458,-0.3710067],"tp":"SU","tags":{"ele":"1154","name":"Los Castillejos","name:ca":"Els Castillejos","name:es":"Los Castillejos"}},"10754067982":{"location":[40.2459314,-0.4708843],"tp":"SU","tags":{"ele":"1045","name":"Peña el Castellar"}},"10771701388":{"location":[40.2781615,-0.4944614],"tp":"SU","tags":{"ele":"1467","name":"Morrón del Solano"}},"10781722917":{"location":[40.2127966,-0.3618706],"tp":"SU","tags":{"ele":"1581","name":"La Golosilla","wikidata":"Q18046866","wikipedia":"ca:La Golosilla"}},"11081985708":{"location":[40.2441754,-0.5478208],"tp":"SU","tags":{"name":"Cabezo la Cruz","not:name":"Cabezo de las Cruces"}},"11100329204":{"location":[40.2143103,-0.3900146],"tp":"SU","tags":{"ele":"1217","name":"Alto de Ramos"}},"11100334093":{"location":[40.2078295,-0.3960349],"tp":"SU","tags":{"ele":"1064","name":"Alto de Borrás"}},"11174873438":{"location":[40.4439676,-0.6975117],"tp":"SU","tags":{"ele":"1688"}},"11174873463":{"location":[40.4408386,-0.6817055],"tp":"SU","tags":{"ele":"1702"}},"11174873464":{"location":[40.4376091,-0.6685732],"tp":"SU","tags":{"ele":"1726"}},"11174873465":{"location":[40.4419822,-0.6617389],"tp":"SU","tags":{"ele":"1673"}},"11174873466":{"location":[40.4445053,-0.6583364],"tp":"SU","tags":{"ele":"1753"}},"11174873467":{"location":[40.4389344,-0.6432652],"tp":"SU","tags":{"ele":"1734"}},"11174873516":{"location":[40.4179576,-0.634854],"tp":"SU","tags":{"ele":"1921"}},"11174873522":{"location":[40.3983008,-0.6368065],"tp":"SU","tags":{"ele":"1878"}},"11174873528":{"location":[40.394694,-0.648129],"tp":"SU","tags":{"ele":"1856"}},"11174874938":{"location":[40.3901656,-0.6653107],"tp":"SU","tags":{"ele":"2021","name":"Peñarroya","name:ru":"Пеньярроя","prominence":"1018","wikidata":"Q6075083"}},"11175084500":{"location":[40.4253697,-0.6114152],"tp":"SU","tags":{"ele":"1972"}},"11386070188":{"location":[40.4017389,-0.4104209],"tp":"SU","tags":{}},"11535280757":{"location":[40.2685836,-0.3844835],"tp":"SU","tags":{"ele":"1598","name":"Collet Roig"}},"11538238151":{"location":[40.3075617,-0.3806779],"tp":"SU","tags":{"ele":"1184","name":"Penya de la Veja"}},"11592749850":{"location":[40.2985859,-0.3938073],"tp":"SU","tags":{"ele":"1203","name":"el Castellet"}},"11592757320":{"location":[40.3069595,-0.3735124],"tp":"SU","tags":{"ele":"1162","name":"Penya la Veja"}},"11990769976":{"location":[40.184357,-0.6304345],"tp":"SU","tags":{"name":"1193"}},"12071404923":{"location":[40.2468096,-0.3844333],"tp":"SU","tags":{"ele":"1231","name":"la Coronica"}},"12071549686":{"location":[40.2383037,-0.3721319],"tp":"SU","tags":{"ele":"1593","name":"Roques de Marcén"}},"12083682248":{"location":[40.20448,-0.5378645],"tp":"SU","tags":{"ele":"1216","name":"El Cremadal","source":"Acadèmia Valenciana de la Llengua"}},"12083688586":{"location":[40.2123921,-0.5246279],"tp":"SU","tags":{"ele":"1315","name":"Alto de la Fuente de la Hoya","source":"Acadèmia Valenciana de la Llengua"}},"12083688587":{"location":[40.212389,-0.508805],"tp":"SU","tags":{"ele":"1344","name":"Alto del Contador","source":"Acadèmia Valenciana de la Llengua"}},"12138393681":{"location":[40.3865484,-0.3861859],"tp":"SU","tags":{"ele":"1566","name":"Moleta Los Lores"}},"12269870942":{"location":[40.3052545,-0.3722477],"tp":"SU","tags":{"ele":"1132","name":"Tormo de l'Assor"}},"12476300284":{"location":[40.3904779,-0.4441637],"tp":"SU","tags":{"ele":"1657","name":"Cabecico del Masico Espartero"}},"12476300285":{"location":[40.4245646,-0.3674805],"tp":"SU","tags":{"ele":"1455","name":"Tozal del Masico Targa"}},"12476300286":{"location":[40.3855701,-0.4799149],"tp":"SU","tags":{"ele":"1753","name":"La Muela"}},"12476300287":{"location":[40.3778851,-0.4864719],"tp":"SU","tags":{"ele":"1668","name":"El Bertolín"}},"12476310021":{"location":[40.4274428,-0.3516171],"tp":"SU","tags":{"ele":"1490","name":"Moleta del Mas de Saura"}},"12568234750":{"location":[40.3123352,-0.5807066],"tp":"SU","tags":{"ele":"1513","name":"Cerro del Masico Royo"}},"12750294020":{"location":[40.1834964,-0.3703594],"tp":"SU","tags":{"name":"Alto de la Serratilla"}},"12846468619":{"location":[40.1790037,-0.4278008],"tp":"SU","tags":{"ele":"1310","name":"El Tis"}},"12846509972":{"location":[40.2094378,-0.4894879],"tp":"SU","tags":{"ele":"1340","name":"Cabezo Blanco"}},"12954703333":{"location":[40.2525642,-0.4380862],"tp":"SU","tags":{"ele":"1505","name":"El Salgar"}},"12988616217":{"location":[40.2560756,-0.4549938],"tp":"SU","tags":{"alt_name":"Las Horcas","ele":"1502","name":"Cerro las Horcas"}},"12988616228":{"location":[40.2303158,-0.5053389],"tp":"SU","tags":{"ele":"1514"}},"12988616229":{"location":[40.2317697,-0.5103332],"tp":"SU","tags":{"ele":"1503"}},"12988616230":{"location":[40.2306189,-0.5074793],"tp":"SU","tags":{"ele":"1514"}},"13323124833":{"location":[40.3139513,-0.5855584],"tp":"SU","tags":{"alt_name":"L'Algezar","ele":"1439","name":"Tozal del Aljezar"}},"13404281561":{"location":[40.4182991,-0.4451394],"tp":"SU","tags":{"ele":"1579","name":"Loma de Valdecanales"}},"13404281590":{"location":[40.4390023,-0.4446244],"tp":"SU","tags":{"ele":"1544","name":"Loma del Masico Lomos"}},"13406453390":{"location":[40.3810582,-0.3936625],"tp":"SU","tags":{"ele":"1577","name":"Cabecico de Valdelagua"}},"13406475954":{"location":[40.3770861,-0.3987479],"tp":"SU","tags":{"ele":"1536","name":"Loma la Balsilla"}},"13406476324":{"location":[40.3792193,-0.4475319],"tp":"SU","tags":{"ele":"1593","name":"Coronica de la Bolasa"}},"13406476494":{"location":[40.4014052,-0.4555249],"tp":"SU","tags":{"ele":"1582","name":"La Coroneta"}},"13406476500":{"location":[40.4093952,-0.4486478],"tp":"SU","tags":{"ele":"1591","name":"Cabecico del Mas de Grau"}},"13406732467":{"location":[40.385978,-0.372591],"tp":"SU","tags":{"ele":"1468","name":"Loma Malaño"}},"13625167447":{"location":[40.266084,-0.4730086],"tp":"SU","tags":{"name":"el Tormoroyo"}},"13626869279":{"location":[40.2691806,-0.5820172],"tp":"SU","tags":{"ele":"1561","name":"Peña Calva"}},"13626869285":{"location":[40.2499845,-0.563901],"tp":"SU","tags":{"ele":"1568","name":"Loma del Mosquito"}},"13630054741":{"location":[40.1854673,-0.6213909],"tp":"SU","tags":{"ele":"1241","name":"Peñaroya"}}}