{"1848313650":{"location":[40.837103,31.4346675],"tp":"SU","ts":"2023-12-14T12:41:45Z","tags":{"ele":"1384","name":"Karadikmen Tepesi","source":"HGK","wikidata":"Q31565637"}},"2297389288":{"location":[40.890128,31.5791538],"tp":"SU","ts":"2021-04-23T14:28:10Z","tags":{"ele":"1657","name":"Tüllükırış Tepesi"}},"3624892040":{"location":[40.913285,31.5505625],"tp":"SU","ts":"2021-04-23T14:28:10Z","tags":{"ele":"1469","source":"cyclemap"}},"3624892069":{"location":[40.9283174,31.5940221],"tp":"SU","ts":"2021-04-22T13:10:17Z","tags":{"ele":"1427","source":"cyclemap"}},"8717934348":{"location":[40.9185392,31.5038109],"tp":"SU","ts":"2021-05-10T14:44:53Z","tags":{"ele":"1102","source":"Thunderforest Landschaft"}},"8717934349":{"location":[40.9214273,31.4931223],"tp":"SU","ts":"2021-05-10T14:44:53Z","tags":{"ele":"1073","source":"Thunderforest Landschaft"}},"8717934350":{"location":[40.8917396,31.4664423],"tp":"SU","ts":"2021-05-10T14:44:53Z","tags":{"ele":"1101","source":"Thunderforest Landschaft"}},"8717934351":{"location":[40.9016134,31.4647311],"tp":"SU","ts":"2021-05-10T14:44:53Z","tags":{"ele":"1095","source":"Thunderforest Landschaft"}},"8717934352":{"location":[40.8847765,31.4321262],"tp":"SU","ts":"2021-05-10T14:44:53Z","tags":{"ele":"984","source":"Thunderforest Landschaft"}},"8717934353":{"location":[40.8736468,31.4205819],"tp":"SU","ts":"2021-05-10T14:44:53Z","tags":{"ele":"1078","source":"Thunderforest Landschaft"}},"8717934354":{"location":[40.8862425,31.4249083],"tp":"SU","ts":"2021-05-10T14:44:53Z","tags":{"ele":"1079","source":"Thunderforest Landschaft"}},"8717934355":{"location":[40.8898012,31.424911],"tp":"SU","ts":"2021-05-10T14:44:53Z","tags":{"ele":"1053","source":"Thunderforest Landschaft"}},"8717934356":{"location":[40.8897363,31.3580006],"tp":"SU","ts":"2021-05-10T14:44:53Z","tags":{"ele":"964","source":"Thunderforest Landschaft"}},"8717934357":{"location":[40.8910381,31.3616377],"tp":"SU","ts":"2021-05-10T14:44:53Z","tags":{"ele":"959","source":"Thunderforest Landschaft"}},"8717934358":{"location":[40.873225,31.3521856],"tp":"SU","ts":"2021-05-10T14:19:25Z","tags":{"ele":"932","source":"Thunderforest Landschaft"}},"11140465285":{"location":[40.8141422,31.5912187],"tp":"SU","ts":"2023-08-24T07:58:34Z","tags":{"ele":"1770","name":"Fenerlik Tepe","source":"cyclOSM"}}}